{"version": 0.6, "generator": "Overpass API 0.7.62.1 084b4234", "osm3s": {"timestamp_osm_base": "2024-05-07T23:37:13Z", "copyright": "The data included in this document is from www.openstreetmap.org. The data is made available under ODbL."}, "elements": [{"type": "node", "id": 429529483, "lat": 26.7259653, "lon": 0.1726833}, {"type": "node", "id": 429529484, "lat": 26.7261004, "lon": 0.1735298}, {"type": "node", "id": 429529485, "lat": 26.7261533, "lon": 0.1739306}, {"type": "node", "id": 429529489, "lat": 26.7263338, "lon": 0.1769954}, {"type": "node", "id": 429529490, "lat": 26.7264133, "lon": 0.1776679}, {"type": "node", "id": 429529491, "lat": 26.7265548, "lon": 0.1784664}, {"type": "node", "id": 429529492, "lat": 26.7267262, "lon": 0.1791213}, {"type": "node", "id": 429529493, "lat": 26.7269343, "lon": 0.1797445}, {"type": "node", "id": 429529498, "lat": 26.7295613, "lon": 0.1834572}, {"type": "node", "id": 429529499, "lat": 26.7299123, "lon": 0.1840493}, {"type": "node", "id": 429529502, "lat": 26.7301501, "lon": 0.1852103}, {"type": "node", "id": 429529504, "lat": 26.7300452, "lon": 0.1865911}, {"type": "node", "id": 429529505, "lat": 26.7300401, "lon": 0.1873382}, {"type": "node", "id": 429529506, "lat": 26.7300757, "lon": 0.1877268}, {"type": "node", "id": 429529507, "lat": 26.7301515, "lon": 0.1881659}, {"type": "node", "id": 429529509, "lat": 26.7310066, "lon": 0.1905548}, {"type": "node", "id": 429529511, "lat": 26.7311989, "lon": 0.1913875}, {"type": "node", "id": 429529513, "lat": 26.7314096, "lon": 0.1921851}, {"type": "node", "id": 429529514, "lat": 26.7321264, "lon": 0.1939965}, {"type": "node", "id": 429529515, "lat": 26.7326423, "lon": 0.1949974}, {"type": "node", "id": 429529516, "lat": 26.733474, "lon": 0.1961955}, {"type": "node", "id": 429529517, "lat": 26.7341755, "lon": 0.1969966}, {"type": "node", "id": 429529518, "lat": 26.7348989, "lon": 0.1977156}, {"type": "node", "id": 429529519, "lat": 26.7357267, "lon": 0.1984233}, {"type": "node", "id": 429529520, "lat": 26.7367718, "lon": 0.1991715}, {"type": "node", "id": 429529521, "lat": 26.7374659, "lon": 0.1996583}, {"type": "node", "id": 429529522, "lat": 26.7380927, "lon": 0.2001704}, {"type": "node", "id": 429529523, "lat": 26.7392407, "lon": 0.2013706}, {"type": "node", "id": 429529524, "lat": 26.7400391, "lon": 0.2025446}, {"type": "node", "id": 429529525, "lat": 26.7408321, "lon": 0.2041731}, {"type": "node", "id": 429529528, "lat": 26.7469392, "lon": 0.2193507}, {"type": "node", "id": 429529529, "lat": 26.7474149, "lon": 0.2205778}, {"type": "node", "id": 429529530, "lat": 26.7478057, "lon": 0.2213387}, {"type": "node", "id": 429529531, "lat": 26.7485434, "lon": 0.2223344}, {"type": "node", "id": 429529532, "lat": 26.7490332, "lon": 0.2228076}, {"type": "node", "id": 429529533, "lat": 26.7503669, "lon": 0.2239749}, {"type": "node", "id": 429529535, "lat": 26.7509773, "lon": 0.224573}, {"type": "node", "id": 429529536, "lat": 26.7515317, "lon": 0.2252958}, {"type": "node", "id": 429529537, "lat": 26.7520173, "lon": 0.2261116}, {"type": "node", "id": 429529538, "lat": 26.7523781, "lon": 0.2269714}, {"type": "node", "id": 429529539, "lat": 26.7526014, "lon": 0.2276997}, {"type": "node", "id": 429529540, "lat": 26.7533551, "lon": 0.2306048}, {"type": "node", "id": 429529541, "lat": 26.7536957, "lon": 0.231698}, {"type": "node", "id": 429529542, "lat": 26.754193, "lon": 0.2331454}, {"type": "node", "id": 429529543, "lat": 26.7546889, "lon": 0.2346275}, {"type": "node", "id": 429529544, "lat": 26.7551778, "lon": 0.2364365}, {"type": "node", "id": 429529548, "lat": 26.7557743, "lon": 0.2392901}, {"type": "node", "id": 429529550, "lat": 26.7560704, "lon": 0.2406246}, {"type": "node", "id": 429529551, "lat": 26.7564347, "lon": 0.242023}, {"type": "node", "id": 429529552, "lat": 26.7570594, "lon": 0.2441498}, {"type": "node", "id": 429529554, "lat": 26.7578525, "lon": 0.2472676}, {"type": "node", "id": 429529556, "lat": 26.758292, "lon": 0.2496381}, {"type": "node", "id": 429529562, "lat": 26.7586674, "lon": 0.2520942}, {"type": "node", "id": 429529568, "lat": 26.7589339, "lon": 0.2547162}, {"type": "node", "id": 429529570, "lat": 26.7592598, "lon": 0.2587874}, {"type": "node", "id": 429529573, "lat": 26.7594328, "lon": 0.2604698}, {"type": "node", "id": 429529575, "lat": 26.7596977, "lon": 0.262384}, {"type": "node", "id": 429529577, "lat": 26.7600221, "lon": 0.2642475}, {"type": "node", "id": 429529581, "lat": 26.7604799, "lon": 0.2664123}, {"type": "node", "id": 429529584, "lat": 26.7609318, "lon": 0.2682209}, {"type": "node", "id": 429529586, "lat": 26.7616237, "lon": 0.2707357}, {"type": "node", "id": 429529589, "lat": 26.7623677, "lon": 0.2735825}, {"type": "node", "id": 429529591, "lat": 26.7627947, "lon": 0.2753253}, {"type": "node", "id": 429529593, "lat": 26.7632257, "lon": 0.2771793}, {"type": "node", "id": 429529596, "lat": 26.7637566, "lon": 0.2795762}, {"type": "node", "id": 429529599, "lat": 26.7643381, "lon": 0.2821361}, {"type": "node", "id": 429529603, "lat": 26.7654062, "lon": 0.2864451}, {"type": "node", "id": 429529605, "lat": 26.7664288, "lon": 0.2901202}, {"type": "node", "id": 429529606, "lat": 26.7669073, "lon": 0.2917508}, {"type": "node", "id": 429529607, "lat": 26.7675469, "lon": 0.2938343}, {"type": "node", "id": 429529618, "lat": 26.7690396, "lon": 0.2984151}, {"type": "node", "id": 429529621, "lat": 26.7706311, "lon": 0.3030831}, {"type": "node", "id": 429529624, "lat": 26.7710131, "lon": 0.3041803}, {"type": "node", "id": 429529627, "lat": 26.7713866, "lon": 0.3050505}, {"type": "node", "id": 429529630, "lat": 26.7718186, "lon": 0.3059948}, {"type": "node", "id": 429529632, "lat": 26.772356, "lon": 0.3069058}, {"type": "node", "id": 429529635, "lat": 26.7728246, "lon": 0.3076261}, {"type": "node", "id": 429529646, "lat": 26.7751006, "lon": 0.3110367}, {"type": "node", "id": 429529649, "lat": 26.7763324, "lon": 0.3136687}, {"type": "node", "id": 429529651, "lat": 26.7797677, "lon": 0.3229885}, {"type": "node", "id": 429529653, "lat": 26.7818009, "lon": 0.3278579}, {"type": "node", "id": 429529655, "lat": 26.7833587, "lon": 0.3309923}, {"type": "node", "id": 429529656, "lat": 26.7859628, "lon": 0.3355248}, {"type": "node", "id": 429529657, "lat": 26.7874311, "lon": 0.3382043}, {"type": "node", "id": 429529658, "lat": 26.7889378, "lon": 0.3414352}, {"type": "node", "id": 429529666, "lat": 26.7902661, "lon": 0.3448396}, {"type": "node", "id": 429529668, "lat": 26.7925706, "lon": 0.3516919}, {"type": "node", "id": 429529670, "lat": 26.7944317, "lon": 0.3570771}, {"type": "node", "id": 429529671, "lat": 26.7958312, "lon": 0.3612329}, {"type": "node", "id": 429529673, "lat": 26.798041, "lon": 0.3659784}, {"type": "node", "id": 429529674, "lat": 26.7987412, "lon": 0.367692}, {"type": "node", "id": 429529675, "lat": 26.8023793, "lon": 0.3803537}, {"type": "node", "id": 429529676, "lat": 26.8035411, "lon": 0.3837554}, {"type": "node", "id": 429529677, "lat": 26.8052659, "lon": 0.3883778}, {"type": "node", "id": 429529678, "lat": 26.8073153, "lon": 0.3932602}, {"type": "node", "id": 429529680, "lat": 26.8092119, "lon": 0.3982707}, {"type": "node", "id": 429529681, "lat": 26.8113878, "lon": 0.4033711}, {"type": "node", "id": 429529683, "lat": 26.8128823, "lon": 0.4063757}, {"type": "node", "id": 429529684, "lat": 26.8144747, "lon": 0.4098948}, {"type": "node", "id": 429529685, "lat": 26.8162682, "lon": 0.4140628}, {"type": "node", "id": 429529687, "lat": 26.8178228, "lon": 0.4176527}, {"type": "node", "id": 429529688, "lat": 26.8184454, "lon": 0.4190065}, {"type": "node", "id": 429529690, "lat": 26.8203367, "lon": 0.4230931}, {"type": "node", "id": 429529691, "lat": 26.8224203, "lon": 0.4275531}, {"type": "node", "id": 429529693, "lat": 26.8261676, "lon": 0.4344142}, {"type": "node", "id": 429529695, "lat": 26.8294355, "lon": 0.4398275}, {"type": "node", "id": 429529696, "lat": 26.8303244, "lon": 0.4413817}, {"type": "node", "id": 429529697, "lat": 26.8313655, "lon": 0.4433277}, {"type": "node", "id": 429529699, "lat": 26.8336386, "lon": 0.4483078}, {"type": "node", "id": 429529701, "lat": 26.834862, "lon": 0.4508445}, {"type": "node", "id": 429529702, "lat": 26.836838, "lon": 0.4544546}, {"type": "node", "id": 429529704, "lat": 26.8397985, "lon": 0.4593132}, {"type": "node", "id": 429529706, "lat": 26.8409785, "lon": 0.461584}, {"type": "node", "id": 429529707, "lat": 26.8427409, "lon": 0.4648005}, {"type": "node", "id": 429529708, "lat": 26.8447886, "lon": 0.4679559}, {"type": "node", "id": 429529709, "lat": 26.8472881, "lon": 0.4714664}, {"type": "node", "id": 429529710, "lat": 26.8493702, "lon": 0.4748034}, {"type": "node", "id": 429529711, "lat": 26.8523196, "lon": 0.4795881}, {"type": "node", "id": 429529712, "lat": 26.8538165, "lon": 0.4822319}, {"type": "node", "id": 429529714, "lat": 26.8546201, "lon": 0.4846123}, {"type": "node", "id": 429529716, "lat": 26.8550891, "lon": 0.4868385}, {"type": "node", "id": 429529717, "lat": 26.8556967, "lon": 0.4893417}, {"type": "node", "id": 429529719, "lat": 26.8566671, "lon": 0.4921795}, {"type": "node", "id": 429529720, "lat": 26.8574676, "lon": 0.4940567}, {"type": "node", "id": 429529722, "lat": 26.8585923, "lon": 0.4962488}, {"type": "node", "id": 429529724, "lat": 26.8593782, "lon": 0.4976947}, {"type": "node", "id": 429529725, "lat": 26.860694, "lon": 0.5011078}, {"type": "node", "id": 429529727, "lat": 26.8610967, "lon": 0.5032981}, {"type": "node", "id": 429529728, "lat": 26.8616326, "lon": 0.5067115}, {"type": "node", "id": 429529730, "lat": 26.8622136, "lon": 0.5084441}, {"type": "node", "id": 429529732, "lat": 26.8635733, "lon": 0.5114012}, {"type": "node", "id": 429529733, "lat": 26.8641892, "lon": 0.5133292}, {"type": "node", "id": 429529735, "lat": 26.8642473, "lon": 0.515153}, {"type": "node", "id": 429529736, "lat": 26.8640382, "lon": 0.5192825}, {"type": "node", "id": 429529738, "lat": 26.8642938, "lon": 0.5205722}, {"type": "node", "id": 429529739, "lat": 26.8649097, "lon": 0.522422}, {"type": "node", "id": 429529740, "lat": 26.8651886, "lon": 0.523881}, {"type": "node", "id": 429529741, "lat": 26.8649562, "lon": 0.5261867}, {"type": "node", "id": 429529742, "lat": 26.8645767, "lon": 0.5288379}, {"type": "node", "id": 429529743, "lat": 26.8644916, "lon": 0.5312094}, {"type": "node", "id": 429529745, "lat": 26.8647834, "lon": 0.5339756}, {"type": "node", "id": 429529747, "lat": 26.8665815, "lon": 0.5434323}, {"type": "node", "id": 429529749, "lat": 26.8673731, "lon": 0.5467287}, {"type": "node", "id": 429529750, "lat": 26.8696538, "lon": 0.5543002}, {"type": "node", "id": 429529752, "lat": 26.8709452, "lon": 0.5596696}, {"type": "node", "id": 429529753, "lat": 26.8722638, "lon": 0.5675624}, {"type": "node", "id": 429529755, "lat": 26.8729635, "lon": 0.572021}, {"type": "node", "id": 429529756, "lat": 26.8761982, "lon": 0.5879094}, {"type": "node", "id": 429529758, "lat": 26.8771379, "lon": 0.5933816}, {"type": "node", "id": 429529760, "lat": 26.8779828, "lon": 0.5973017}, {"type": "node", "id": 429529762, "lat": 26.8801279, "lon": 0.6051207}, {"type": "node", "id": 429529764, "lat": 26.8811451, "lon": 0.6094063}, {"type": "node", "id": 429529766, "lat": 26.8823317, "lon": 0.6145239}, {"type": "node", "id": 429529768, "lat": 26.8828102, "lon": 0.6169379}, {"type": "node", "id": 429529770, "lat": 26.8839492, "lon": 0.6247206}, {"type": "node", "id": 429529772, "lat": 26.8847626, "lon": 0.6302996}, {"type": "node", "id": 429529774, "lat": 26.8853941, "lon": 0.6340546}, {"type": "node", "id": 429529776, "lat": 26.8861501, "lon": 0.6380029}, {"type": "node", "id": 429529778, "lat": 26.8880065, "lon": 0.6468434}, {"type": "node", "id": 429529780, "lat": 26.8887242, "lon": 0.6509418}, {"type": "node", "id": 429529781, "lat": 26.8918776, "lon": 0.6731688}, {"type": "node", "id": 429529783, "lat": 26.8936023, "lon": 0.6811453}, {"type": "node", "id": 429529784, "lat": 26.8949518, "lon": 0.6855754}, {"type": "node", "id": 429529785, "lat": 26.8959577, "lon": 0.689236}, {"type": "node", "id": 429529788, "lat": 26.8975803, "lon": 0.6958729}, {"type": "node", "id": 429529789, "lat": 26.8982423, "lon": 0.6989949}, {"type": "node", "id": 429529792, "lat": 26.9002542, "lon": 0.7105951}, {"type": "node", "id": 429529794, "lat": 26.9015262, "lon": 0.717203}, {"type": "node", "id": 429529796, "lat": 26.9017404, "lon": 0.7185711}, {"type": "node", "id": 429529798, "lat": 26.9020129, "lon": 0.7209436}, {"type": "node", "id": 429529800, "lat": 26.9022076, "lon": 0.7224063}, {"type": "node", "id": 429529801, "lat": 26.9028501, "lon": 0.7258995}, {"type": "node", "id": 429529803, "lat": 26.9042908, "lon": 0.7319397}, {"type": "node", "id": 429529804, "lat": 26.9049332, "lon": 0.7356781}, {"type": "node", "id": 429529816, "lat": 26.905402, "lon": 0.7385105}, {"type": "node", "id": 429529818, "lat": 26.9063587, "lon": 0.7434243}, {"type": "node", "id": 429529820, "lat": 26.9066553, "lon": 0.7452375}, {"type": "node", "id": 429529822, "lat": 26.9071279, "lon": 0.7497867}, {"type": "node", "id": 429529824, "lat": 26.9072367, "lon": 0.7534724}, {"type": "node", "id": 429529827, "lat": 26.9071619, "lon": 0.7560796}, {"type": "node", "id": 429529828, "lat": 26.9069855, "lon": 0.758585}, {"type": "node", "id": 429529830, "lat": 26.9064564, "lon": 0.7625947}, {"type": "node", "id": 429529831, "lat": 26.9058952, "lon": 0.7664066}, {"type": "node", "id": 429529832, "lat": 26.9054248, "lon": 0.7709438}, {"type": "node", "id": 429529833, "lat": 26.9049705, "lon": 0.7745159}, {"type": "node", "id": 429529834, "lat": 26.9042971, "lon": 0.7785796}, {"type": "node", "id": 429529836, "lat": 26.9041314, "lon": 0.7798862}, {"type": "node", "id": 429529837, "lat": 26.9039069, "lon": 0.7823436}, {"type": "node", "id": 429529839, "lat": 26.9037305, "lon": 0.7863293}, {"type": "node", "id": 429529840, "lat": 26.90349, "lon": 0.7898476}, {"type": "node", "id": 429529842, "lat": 26.9031212, "lon": 0.7924668}, {"type": "node", "id": 429529843, "lat": 26.9024905, "lon": 0.7957932}, {"type": "node", "id": 429529845, "lat": 26.9016193, "lon": 0.7994972}, {"type": "node", "id": 429529847, "lat": 26.900887, "lon": 0.8028956}, {"type": "node", "id": 429529848, "lat": 26.9005021, "lon": 0.8051972}, {"type": "node", "id": 429529849, "lat": 26.9001173, "lon": 0.8086435}, {"type": "node", "id": 429529851, "lat": 26.8998768, "lon": 0.8119879}, {"type": "node", "id": 429529853, "lat": 26.8994919, "lon": 0.8151945}, {"type": "node", "id": 429529855, "lat": 26.8988238, "lon": 0.8187307}, {"type": "node", "id": 429529857, "lat": 26.8980274, "lon": 0.8223568}, {"type": "node", "id": 429529859, "lat": 26.8973485, "lon": 0.8253836}, {"type": "node", "id": 429529862, "lat": 26.8966911, "lon": 0.8275952}, {"type": "node", "id": 429529863, "lat": 26.8961138, "lon": 0.8293753}, {"type": "node", "id": 429529866, "lat": 26.895761, "lon": 0.8312693}, {"type": "node", "id": 429529868, "lat": 26.8958014, "lon": 0.8341628}, {"type": "node", "id": 429529869, "lat": 26.8962626, "lon": 0.8366957}, {"type": "node", "id": 429529870, "lat": 26.8973437, "lon": 0.8399406}, {"type": "node", "id": 429529871, "lat": 26.8978307, "lon": 0.8408476}, {"type": "node", "id": 429529872, "lat": 26.8996204, "lon": 0.8430882}, {"type": "node", "id": 429529873, "lat": 26.9019768, "lon": 0.8451207}, {"type": "node", "id": 429529874, "lat": 26.9032668, "lon": 0.8464642}, {"type": "node", "id": 429529877, "lat": 26.904712, "lon": 0.8483944}, {"type": "node", "id": 429529878, "lat": 26.9061095, "lon": 0.850843}, {"type": "node", "id": 429529881, "lat": 26.906911, "lon": 0.8521568}, {"type": "node", "id": 429529882, "lat": 26.9098635, "lon": 0.8560912}, {"type": "node", "id": 429529884, "lat": 26.9110944, "lon": 0.8578581}, {"type": "node", "id": 429529886, "lat": 26.9122197, "lon": 0.859585}, {"type": "node", "id": 429529888, "lat": 26.914189, "lon": 0.8631029}, {"type": "node", "id": 429529890, "lat": 26.9151781, "lon": 0.8651754}, {"type": "node", "id": 429529892, "lat": 26.9166305, "lon": 0.8685236}, {"type": "node", "id": 429529894, "lat": 26.9173167, "lon": 0.869878}, {"type": "node", "id": 429529895, "lat": 26.9182615, "lon": 0.8713851}, {"type": "node", "id": 429529897, "lat": 26.9201471, "lon": 0.8749424}, {"type": "node", "id": 429529898, "lat": 26.9203947, "lon": 0.8770394}, {"type": "node", "id": 429529900, "lat": 26.9201451, "lon": 0.8788553}, {"type": "node", "id": 429529902, "lat": 26.9196189, "lon": 0.8803037}, {"type": "node", "id": 429529903, "lat": 26.9186882, "lon": 0.8824571}, {"type": "node", "id": 429529905, "lat": 26.9181139, "lon": 0.8840448}, {"type": "node", "id": 429529907, "lat": 26.9172943, "lon": 0.8886078}, {"type": "node", "id": 429529908, "lat": 26.9170791, "lon": 0.8903849}, {"type": "node", "id": 429529910, "lat": 26.9167244, "lon": 0.8921636}, {"type": "node", "id": 429529912, "lat": 26.9160937, "lon": 0.8952919}, {"type": "node", "id": 429529913, "lat": 26.9157637, "lon": 0.8979204}, {"type": "node", "id": 429529914, "lat": 26.9156297, "lon": 0.9001842}, {"type": "node", "id": 429529916, "lat": 26.9158211, "lon": 0.9046528}, {"type": "node", "id": 429529917, "lat": 26.9163951, "lon": 0.9084615}, {"type": "node", "id": 429529918, "lat": 26.9165213, "lon": 0.9099278}, {"type": "node", "id": 429529919, "lat": 26.9164319, "lon": 0.9127348}, {"type": "node", "id": 429529920, "lat": 26.9158451, "lon": 0.915236}, {"type": "node", "id": 429529922, "lat": 26.9150371, "lon": 0.9173572}, {"type": "node", "id": 429529923, "lat": 26.9144252, "lon": 0.9189128}, {"type": "node", "id": 429529926, "lat": 26.9137033, "lon": 0.9202462}, {"type": "node", "id": 429529928, "lat": 26.9129038, "lon": 0.9213674}, {"type": "node", "id": 429529930, "lat": 26.9121048, "lon": 0.9226949}, {"type": "node", "id": 429529932, "lat": 26.9109582, "lon": 0.9243058}, {"type": "node", "id": 429529934, "lat": 26.9097983, "lon": 0.9269226}, {"type": "node", "id": 429529936, "lat": 26.9092774, "lon": 0.9286246}, {"type": "node", "id": 429529938, "lat": 26.9088123, "lon": 0.9309904}, {"type": "node", "id": 429529941, "lat": 26.9086892, "lon": 0.9332412}, {"type": "node", "id": 429529942, "lat": 26.9087106, "lon": 0.9349244}, {"type": "node", "id": 429529945, "lat": 26.9089959, "lon": 0.9382185}, {"type": "node", "id": 429529946, "lat": 26.9096331, "lon": 0.9413739}, {"type": "node", "id": 429529949, "lat": 26.9104095, "lon": 0.9439653}, {"type": "node", "id": 429529950, "lat": 26.9108479, "lon": 0.9457182}, {"type": "node", "id": 429529954, "lat": 26.9123046, "lon": 0.9510719}, {"type": "node", "id": 429529958, "lat": 26.9133984, "lon": 0.9539435}, {"type": "node", "id": 429529961, "lat": 26.9140942, "lon": 0.9558512}, {"type": "node", "id": 429529962, "lat": 26.9144448, "lon": 0.9568928}, {"type": "node", "id": 429529965, "lat": 26.9149954, "lon": 0.9587303}, {"type": "node", "id": 429529982, "lat": 26.9154898, "lon": 0.9608542}, {"type": "node", "id": 429529987, "lat": 26.9158056, "lon": 0.96274}, {"type": "node", "id": 429529989, "lat": 26.915977, "lon": 0.9642785}, {"type": "node", "id": 429529993, "lat": 26.9162442, "lon": 0.966147}, {"type": "node", "id": 429529994, "lat": 26.916541, "lon": 0.9677583}, {"type": "node", "id": 429529996, "lat": 26.9168243, "lon": 0.9689372}, {"type": "node", "id": 429529997, "lat": 26.9171623, "lon": 0.9701599}, {"type": "node", "id": 429529998, "lat": 26.9174604, "lon": 0.9711215}, {"type": "node", "id": 429530000, "lat": 26.9179616, "lon": 0.9725131}, {"type": "node", "id": 429530002, "lat": 26.9182676, "lon": 0.9733085}, {"type": "node", "id": 429530005, "lat": 26.9197522, "lon": 0.9764445}, {"type": "node", "id": 429530006, "lat": 26.9206453, "lon": 0.9786726}, {"type": "node", "id": 429530010, "lat": 26.9218926, "lon": 0.9820881}, {"type": "node", "id": 429530014, "lat": 26.9237048, "lon": 0.9865048}, {"type": "node", "id": 429530017, "lat": 26.9247946, "lon": 0.9889169}, {"type": "node", "id": 429530018, "lat": 26.925784, "lon": 0.9912153}, {"type": "node", "id": 429530021, "lat": 26.9275393, "lon": 0.9959441}, {"type": "node", "id": 429530024, "lat": 26.928433, "lon": 0.9983775}, {"type": "node", "id": 429530025, "lat": 26.9290632, "lon": 0.9999354}, {"type": "node", "id": 429530028, "lat": 26.9300281, "lon": 1.0021733}, {"type": "node", "id": 429530030, "lat": 26.9311175, "lon": 1.0044661}, {"type": "node", "id": 429530032, "lat": 26.9321283, "lon": 1.0064748}, {"type": "node", "id": 429530034, "lat": 26.9333544, "lon": 1.009017}, {"type": "node", "id": 429530036, "lat": 26.9342638, "lon": 1.0109592}, {"type": "node", "id": 429530038, "lat": 26.9347476, "lon": 1.0121288}, {"type": "node", "id": 429530039, "lat": 26.9357103, "lon": 1.0144018}, {"type": "node", "id": 429530040, "lat": 26.9364547, "lon": 1.0163712}, {"type": "node", "id": 429530041, "lat": 26.937044, "lon": 1.0179675}, {"type": "node", "id": 429530043, "lat": 26.9376429, "lon": 1.0196804}, {"type": "node", "id": 429530052, "lat": 26.9405438, "lon": 1.0267205}, {"type": "node", "id": 429530059, "lat": 26.9421912, "lon": 1.0300641}, {"type": "node", "id": 429530067, "lat": 26.9445743, "lon": 1.0357512}, {"type": "node", "id": 429530072, "lat": 26.9454913, "lon": 1.037693}, {"type": "node", "id": 429530078, "lat": 26.9472649, "lon": 1.0409846}, {"type": "node", "id": 429530081, "lat": 26.9484328, "lon": 1.042879}, {"type": "node", "id": 429530083, "lat": 26.9493579, "lon": 1.044443}, {"type": "node", "id": 429530087, "lat": 26.95042, "lon": 1.0464059}, {"type": "node", "id": 429530090, "lat": 26.951144, "lon": 1.0478921}, {"type": "node", "id": 429530095, "lat": 26.9519307, "lon": 1.0496454}, {"type": "node", "id": 429530099, "lat": 26.9526926, "lon": 1.0515258}, {"type": "node", "id": 429530103, "lat": 26.9535756, "lon": 1.053989}, {"type": "node", "id": 429530107, "lat": 26.9542987, "lon": 1.0566453}, {"type": "node", "id": 429530110, "lat": 26.9547907, "lon": 1.0585802}, {"type": "node", "id": 429530111, "lat": 26.9551517, "lon": 1.0603586}, {"type": "node", "id": 429530114, "lat": 26.955426, "lon": 1.0618066}, {"type": "node", "id": 429530115, "lat": 26.9556393, "lon": 1.0630795}, {"type": "node", "id": 429530119, "lat": 26.9559779, "lon": 1.0655646}, {"type": "node", "id": 429530121, "lat": 26.9563205, "lon": 1.0676313}, {"type": "node", "id": 429530122, "lat": 26.956545, "lon": 1.0687716}, {"type": "node", "id": 429530123, "lat": 26.9568341, "lon": 1.0700595}, {"type": "node", "id": 429530124, "lat": 26.9574026, "lon": 1.0723632}, {"type": "node", "id": 429530125, "lat": 26.9580693, "lon": 1.0751543}, {"type": "node", "id": 429530127, "lat": 26.9585342, "lon": 1.0773742}, {"type": "node", "id": 429530138, "lat": 26.9587587, "lon": 1.0787234}, {"type": "node", "id": 429530141, "lat": 26.9589017, "lon": 1.0797668}, {"type": "node", "id": 429530142, "lat": 26.9589949, "lon": 1.0804989}, {"type": "node", "id": 429530145, "lat": 26.9590614, "lon": 1.0813954}, {"type": "node", "id": 2118812439, "lat": 26.7272649, "lon": 0.1804121}, {"type": "node", "id": 2338542290, "lat": 26.7580851, "lon": 0.2485223}, {"type": "node", "id": 2956270734, "lat": 26.7387847, "lon": 0.2008285}, {"type": "node", "id": 2956270835, "lat": 26.7317427, "lon": 0.1931578}, {"type": "node", "id": 2956271934, "lat": 26.7300889, "lon": 0.1846192}, {"type": "node", "id": 2956272135, "lat": 26.748176, "lon": 0.2219167}, {"type": "node", "id": 2956300633, "lat": 26.7757725, "lon": 0.3122839}, {"type": "node", "id": 2956407948, "lat": 26.9432915, "lon": 1.0326234}, {"type": "node", "id": 2956407949, "lat": 26.9451817, "lon": 1.0370823}, {"type": "node", "id": 2956408147, "lat": 26.9385902, "lon": 1.0222058}, {"type": "node", "id": 2956408148, "lat": 26.9396342, "lon": 1.0247031}, {"type": "node", "id": 2956408149, "lat": 26.9461464, "lon": 1.0389828}, {"type": "node", "id": 2956408150, "lat": 26.946846, "lon": 1.0402629}, {"type": "node", "id": 2956408151, "lat": 26.958331, "lon": 1.0763398}, {"type": "node", "id": 2956409058, "lat": 26.9264645, "lon": 0.9929793}, {"type": "node", "id": 2956490233, "lat": 26.9115365, "lon": 0.9484161}, {"type": "node", "id": 3012156742, "lat": 26.9579237, "lon": 1.0745418}, {"type": "node", "id": 3012156771, "lat": 26.957172, "lon": 1.0714174}, {"type": "node", "id": 3044821153, "lat": 26.9557313, "lon": 1.0638216}, {"type": "node", "id": 3343029691, "lat": 26.86398, "lon": 0.5179407}, {"type": "node", "id": 3343041912, "lat": 26.8264261, "lon": 0.4348387}, {"type": "node", "id": 3789013335, "lat": 27.8100702, "lon": -0.1957129}, {"type": "node", "id": 3954794592, "lat": 26.8834707, "lon": 0.621223}, {"type": "node", "id": 3954794593, "lat": 26.8903317, "lon": 0.6623788}, {"type": "node", "id": 3954794594, "lat": 26.8924971, "lon": 0.6764863}, {"type": "node", "id": 3954794595, "lat": 26.8991509, "lon": 0.7039872}, {"type": "node", "id": 3954794596, "lat": 26.9010524, "lon": 0.7145831}, {"type": "node", "id": 3954794597, "lat": 26.9025386, "lon": 0.724262}, {"type": "node", "id": 3954794598, "lat": 26.9034472, "lon": 0.7281918}, {"type": "node", "id": 3954794599, "lat": 26.9039599, "lon": 0.7304042}, {"type": "node", "id": 3954794600, "lat": 26.9045313, "lon": 0.7331032}, {"type": "node", "id": 3954794601, "lat": 26.9060286, "lon": 0.7416219}, {"type": "node", "id": 3954814010, "lat": 26.9069904, "lon": 0.7480057}, {"type": "node", "id": 3954814011, "lat": 26.9033884, "lon": 0.7908425}, {"type": "node", "id": 3954814012, "lat": 26.9012344, "lon": 0.8011335}, {"type": "node", "id": 3954814013, "lat": 26.9003044, "lon": 0.8067315}, {"type": "node", "id": 3954814014, "lat": 26.8997485, "lon": 0.8133185}, {"type": "node", "id": 3954814015, "lat": 26.8959695, "lon": 0.8298991}, {"type": "node", "id": 3954814016, "lat": 26.8958679, "lon": 0.8304422}, {"type": "node", "id": 3954814017, "lat": 26.8957213, "lon": 0.832073}, {"type": "node", "id": 3954814018, "lat": 26.8957201, "lon": 0.8330416}, {"type": "node", "id": 3954814019, "lat": 26.8965912, "lon": 0.837926}, {"type": "node", "id": 3954814020, "lat": 26.8968906, "lon": 0.8388449}, {"type": "node", "id": 3954814021, "lat": 26.8985335, "lon": 0.8418714}, {"type": "node", "id": 3954814022, "lat": 26.9040432, "lon": 0.847424}, {"type": "node", "id": 3954814023, "lat": 26.9076834, "lon": 0.8532462}, {"type": "node", "id": 3954814024, "lat": 26.9132871, "lon": 0.8614079}, {"type": "node", "id": 3954814025, "lat": 26.9169274, "lon": 0.8691499}, {"type": "node", "id": 3954814026, "lat": 26.9189427, "lon": 0.8723877}, {"type": "node", "id": 3954814027, "lat": 26.9193421, "lon": 0.8730198}, {"type": "node", "id": 3954814028, "lat": 26.9196864, "lon": 0.8736762}, {"type": "node", "id": 3954814029, "lat": 26.9199818, "lon": 0.8744082}, {"type": "node", "id": 3954814030, "lat": 26.9203049, "lon": 0.875695}, {"type": "node", "id": 3954814031, "lat": 26.9203861, "lon": 0.8764868}, {"type": "node", "id": 3954814032, "lat": 26.9203329, "lon": 0.877839}, {"type": "node", "id": 3954814033, "lat": 26.9178229, "lon": 0.8851535}, {"type": "node", "id": 3954814034, "lat": 26.917603, "lon": 0.8863879}, {"type": "node", "id": 3954814035, "lat": 26.9159646, "lon": 0.8961233}, {"type": "node", "id": 3954814036, "lat": 26.9156085, "lon": 0.9009296}, {"type": "node", "id": 3954814037, "lat": 26.9156871, "lon": 0.9031293}, {"type": "node", "id": 3954814038, "lat": 26.9161128, "lon": 0.9066591}, {"type": "node", "id": 4315960732, "lat": 26.9558264, "lon": 1.064522}, {"type": "node", "id": 4360760404, "lat": 26.7252949, "lon": 0.1707095}, {"type": "node", "id": 4360760410, "lat": 26.7257275, "lon": 0.1718907}, {"type": "node", "id": 5142402089, "lat": 27.0343527, "lon": 1.020846}, {"type": "node", "id": 7069953766, "lat": 27.2668038, "lon": 1.2262094}, {"type": "node", "id": 7069953767, "lat": 27.2667657, "lon": 1.226601}, {"type": "node", "id": 7069953768, "lat": 27.2667704, "lon": 1.2274486}, {"type": "node", "id": 7069953769, "lat": 27.2667228, "lon": 1.2280923}, {"type": "node", "id": 7069953770, "lat": 27.2667013, "lon": 1.2288836}, {"type": "node", "id": 7069953771, "lat": 27.2666655, "lon": 1.2301496}, {"type": "node", "id": 7069953772, "lat": 27.2666393, "lon": 1.2305653}, {"type": "node", "id": 7069953773, "lat": 27.2665058, "lon": 1.2310401}, {"type": "node", "id": 7069953774, "lat": 27.266408, "lon": 1.2312761}, {"type": "node", "id": 7069953775, "lat": 27.2661863, "lon": 1.2315416}, {"type": "node", "id": 7069953776, "lat": 27.2657572, "lon": 1.2317857}, {"type": "node", "id": 7069953777, "lat": 27.2647463, "lon": 1.2323543}, {"type": "node", "id": 7069953778, "lat": 27.2637353, "lon": 1.2328505}, {"type": "node", "id": 7069953779, "lat": 27.2633205, "lon": 1.2330464}, {"type": "node", "id": 7069953780, "lat": 27.2628341, "lon": 1.2331966}, {"type": "node", "id": 7069953781, "lat": 27.2625385, "lon": 1.2332743}, {"type": "node", "id": 7069953782, "lat": 27.262126, "lon": 1.2332717}, {"type": "node", "id": 7069953783, "lat": 27.2616396, "lon": 1.2332234}, {"type": "node", "id": 7069953784, "lat": 27.2613368, "lon": 1.2331885}, {"type": "node", "id": 7069956094, "lat": 27.8498909, "lon": -0.2132262}, {"type": "node", "id": 7069956095, "lat": 27.7197808, "lon": -0.0082413}, {"type": "node", "id": 7069956096, "lat": 27.7177537, "lon": -0.0058794}, {"type": "node", "id": 7069956097, "lat": 27.7096898, "lon": 0.0026822}, {"type": "node", "id": 7069956098, "lat": 27.708683, "lon": 0.0038409}, {"type": "node", "id": 7069956099, "lat": 27.7064698, "lon": 0.0065231}, {"type": "node", "id": 7069956100, "lat": 27.6970847, "lon": 0.0181854}, {"type": "node", "id": 7069956101, "lat": 27.6910714, "lon": 0.0264144}, {"type": "node", "id": 7069956102, "lat": 27.6893614, "lon": 0.0288606}, {"type": "node", "id": 7069956103, "lat": 27.6842596, "lon": 0.0368428}, {"type": "node", "id": 7069956104, "lat": 27.6835946, "lon": 0.0377548}, {"type": "node", "id": 7069956105, "lat": 27.6826065, "lon": 0.0389242}, {"type": "node", "id": 7069956106, "lat": 27.6811339, "lon": 0.0403511}, {"type": "node", "id": 7069956107, "lat": 27.6803358, "lon": 0.0410056}, {"type": "node", "id": 7069956108, "lat": 27.6792432, "lon": 0.0417995}, {"type": "node", "id": 7069956109, "lat": 27.672749, "lon": 0.0461662}, {"type": "node", "id": 7069956110, "lat": 27.6715566, "lon": 0.0468957}, {"type": "node", "id": 7069956111, "lat": 27.6705446, "lon": 0.0474429}, {"type": "node", "id": 7069956112, "lat": 27.6696277, "lon": 0.0478291}, {"type": "node", "id": 7069956113, "lat": 27.6686324, "lon": 0.0481966}, {"type": "node", "id": 7069956114, "lat": 27.6673282, "lon": 0.0485909}, {"type": "node", "id": 7069956115, "lat": 27.6591466, "lon": 0.0498783}, {"type": "node", "id": 7069956116, "lat": 27.6560677, "lon": 0.0505865}, {"type": "node", "id": 7069956117, "lat": 27.6450151, "lon": 0.0539607}, {"type": "node", "id": 7069956118, "lat": 27.6440504, "lon": 0.0543147}, {"type": "node", "id": 7069956119, "lat": 27.6418359, "lon": 0.0554091}, {"type": "node", "id": 7069956120, "lat": 27.6409473, "lon": 0.0559616}, {"type": "node", "id": 7069956121, "lat": 27.6396594, "lon": 0.0569218}, {"type": "node", "id": 7069956122, "lat": 27.6277686, "lon": 0.0670391}, {"type": "node", "id": 7069956123, "lat": 27.6263476, "lon": 0.0684124}, {"type": "node", "id": 7069956124, "lat": 27.625012, "lon": 0.0698125}, {"type": "node", "id": 7069956125, "lat": 27.6234483, "lon": 0.0716954}, {"type": "node", "id": 7069956126, "lat": 27.622607, "lon": 0.0728005}, {"type": "node", "id": 7069956127, "lat": 27.6189543, "lon": 0.0781944}, {"type": "node", "id": 7069956128, "lat": 27.6183768, "lon": 0.0792861}, {"type": "node", "id": 7069956129, "lat": 27.6178967, "lon": 0.0803697}, {"type": "node", "id": 7069956130, "lat": 27.6151779, "lon": 0.087676}, {"type": "node", "id": 7069956131, "lat": 27.6109949, "lon": 0.0974607}, {"type": "node", "id": 7069956132, "lat": 27.607116, "lon": 0.1068162}, {"type": "node", "id": 7069956133, "lat": 27.6017537, "lon": 0.121665}, {"type": "node", "id": 7069956134, "lat": 27.595659, "lon": 0.1375437}, {"type": "node", "id": 7069956135, "lat": 27.594442, "lon": 0.1402581}, {"type": "node", "id": 7069956136, "lat": 27.5888319, "lon": 0.15221}, {"type": "node", "id": 7069956137, "lat": 27.5831264, "lon": 0.1674986}, {"type": "node", "id": 7069956138, "lat": 27.5747197, "lon": 0.1874113}, {"type": "node", "id": 7069956139, "lat": 27.5681528, "lon": 0.2050763}, {"type": "node", "id": 7069956140, "lat": 27.567323, "lon": 0.2072087}, {"type": "node", "id": 7069956141, "lat": 27.5634164, "lon": 0.2168244}, {"type": "node", "id": 7069956142, "lat": 27.5577619, "lon": 0.2298224}, {"type": "node", "id": 7069956143, "lat": 27.552245, "lon": 0.2437591}, {"type": "node", "id": 7069956144, "lat": 27.5502665, "lon": 0.2476644}, {"type": "node", "id": 7069956145, "lat": 27.5479312, "lon": 0.2517843}, {"type": "node", "id": 7069956146, "lat": 27.5465947, "lon": 0.2540374}, {"type": "node", "id": 7069956147, "lat": 27.5456815, "lon": 0.2553463}, {"type": "node", "id": 7069956148, "lat": 27.5421237, "lon": 0.2601635}, {"type": "node", "id": 7069956149, "lat": 27.5414626, "lon": 0.2611399}, {"type": "node", "id": 7069956150, "lat": 27.5408252, "lon": 0.262202}, {"type": "node", "id": 7069956151, "lat": 27.540302, "lon": 0.2632213}, {"type": "node", "id": 7069956152, "lat": 27.5396931, "lon": 0.2645892}, {"type": "node", "id": 7069956153, "lat": 27.5391984, "lon": 0.2659947}, {"type": "node", "id": 7069956154, "lat": 27.5363968, "lon": 0.2772331}, {"type": "node", "id": 7069956155, "lat": 27.5329005, "lon": 0.2885789}, {"type": "node", "id": 7069956156, "lat": 27.5323392, "lon": 0.2905637}, {"type": "node", "id": 7069956157, "lat": 27.5321061, "lon": 0.2916473}, {"type": "node", "id": 7069956158, "lat": 27.5318492, "lon": 0.2933317}, {"type": "node", "id": 7069956159, "lat": 27.5317446, "lon": 0.2945709}, {"type": "node", "id": 7069956160, "lat": 27.531697, "lon": 0.2962446}, {"type": "node", "id": 7069956161, "lat": 27.5318112, "lon": 0.3010511}, {"type": "node", "id": 7069956162, "lat": 27.5319444, "lon": 0.3128314}, {"type": "node", "id": 7069956163, "lat": 27.798815, "lon": -0.163412}, {"type": "node", "id": 7069956164, "lat": 27.526207, "lon": 0.792768}, {"type": "node", "id": 7069956165, "lat": 27.526637, "lon": 0.537692}, {"type": "node", "id": 7069956166, "lat": 27.527342, "lon": 0.777332}, {"type": "node", "id": 7069956167, "lat": 27.499847, "lon": 0.839988}, {"type": "node", "id": 7069956168, "lat": 27.489538, "lon": 0.842113}, {"type": "node", "id": 7069956169, "lat": 27.212122, "lon": 0.905905}, {"type": "node", "id": 7069956170, "lat": 27.531142, "lon": 0.348385}, {"type": "node", "id": 7069956171, "lat": 27.430352, "lon": 0.860053}, {"type": "node", "id": 7069956172, "lat": 27.7676967, "lon": -0.0896402}, {"type": "node", "id": 7069956173, "lat": 27.823747, "lon": -0.215883}, {"type": "node", "id": 7069956174, "lat": 27.237892, "lon": 0.889183}, {"type": "node", "id": 7069956175, "lat": 27.523613, "lon": 0.799317}, {"type": "node", "id": 7069956176, "lat": 27.063783, "lon": 1.005767}, {"type": "node", "id": 7069956177, "lat": 27.530793, "lon": 0.374973}, {"type": "node", "id": 7069956178, "lat": 27.266653, "lon": 0.881043}, {"type": "node", "id": 7069956179, "lat": 27.505927, "lon": 0.836825}, {"type": "node", "id": 7069956180, "lat": 27.527445, "lon": 0.500092}, {"type": "node", "id": 7069956181, "lat": 27.307413, "lon": 0.87936}, {"type": "node", "id": 7069956182, "lat": 27.8164474, "lon": -0.2126148}, {"type": "node", "id": 7069956183, "lat": 27.321698, "lon": 0.879037}, {"type": "node", "id": 7069956184, "lat": 27.202698, "lon": 0.915863}, {"type": "node", "id": 7069956185, "lat": 27.530237, "lon": 0.403477}, {"type": "node", "id": 7069956186, "lat": 27.19403, "lon": 0.921148}, {"type": "node", "id": 7069956187, "lat": 27.130085, "lon": 0.97561}, {"type": "node", "id": 7069956188, "lat": 27.52712, "lon": 0.778907}, {"type": "node", "id": 7069956189, "lat": 27.1792909, "lon": 0.9323079}, {"type": "node", "id": 7069956190, "lat": 27.526442, "lon": 0.525225}, {"type": "node", "id": 7069956191, "lat": 27.522492, "lon": 0.68809}, {"type": "node", "id": 7069956192, "lat": 27.524375, "lon": 0.586047}, {"type": "node", "id": 7069956193, "lat": 27.118157, "lon": 0.979453}, {"type": "node", "id": 7069956194, "lat": 27.835197, "lon": -0.216392}, {"type": "node", "id": 7069956195, "lat": 27.167553, "lon": 0.940905}, {"type": "node", "id": 7069956196, "lat": 27.176377, "lon": 0.934222}, {"type": "node", "id": 7069956197, "lat": 27.527988, "lon": 0.454367}, {"type": "node", "id": 7069956198, "lat": 27.523597, "lon": 0.625877}, {"type": "node", "id": 7069956199, "lat": 27.1989265, "lon": 0.9189794}, {"type": "node", "id": 7069956200, "lat": 27.503193, "lon": 0.83875}, {"type": "node", "id": 7069956201, "lat": 27.140352, "lon": 0.96149}, {"type": "node", "id": 7069956202, "lat": 27.78447, "lon": -0.12905}, {"type": "node", "id": 7069956203, "lat": 27.773602, "lon": -0.1031239}, {"type": "node", "id": 7069956204, "lat": 27.839735, "lon": -0.215733}, {"type": "node", "id": 7069956205, "lat": 27.473093, "lon": 0.84835}, {"type": "node", "id": 7069956206, "lat": 27.12899, "lon": 0.97626}, {"type": "node", "id": 7069956207, "lat": 27.523942, "lon": 0.635218}, {"type": "node", "id": 7069956208, "lat": 27.281668, "lon": 0.880922}, {"type": "node", "id": 7069956209, "lat": 27.52143, "lon": 0.705475}, {"type": "node", "id": 7069956210, "lat": 27.52549, "lon": 0.764792}, {"type": "node", "id": 7069956211, "lat": 27.182918, "lon": 0.930205}, {"type": "node", "id": 7069956212, "lat": 27.508488, "lon": 0.833703}, {"type": "node", "id": 7069956213, "lat": 27.524305, "lon": 0.587635}, {"type": "node", "id": 7069956214, "lat": 27.531125, "lon": 0.335303}, {"type": "node", "id": 7069956215, "lat": 27.440965, "lon": 0.857597}, {"type": "node", "id": 7069956216, "lat": 27.525577, "lon": 0.571743}, {"type": "node", "id": 7069956217, "lat": 27.048292, "lon": 1.013605}, {"type": "node", "id": 7069956218, "lat": 27.10748, "lon": 0.982455}, {"type": "node", "id": 7069956219, "lat": 27.525442, "lon": 0.55306}, {"type": "node", "id": 7069956220, "lat": 27.74148, "lon": -0.033898}, {"type": "node", "id": 7069956221, "lat": 27.20576, "lon": 0.912072}, {"type": "node", "id": 7069956222, "lat": 27.80962, "lon": -0.19318}, {"type": "node", "id": 7069956223, "lat": 27.522468, "lon": 0.685155}, {"type": "node", "id": 7069956224, "lat": 27.0407385, "lon": 1.0173164}, {"type": "node", "id": 7069956225, "lat": 27.531222, "lon": 0.329163}, {"type": "node", "id": 7069956226, "lat": 27.516682, "lon": 0.810762}, {"type": "node", "id": 7069956227, "lat": 27.201662, "lon": 0.916813}, {"type": "node", "id": 7069956228, "lat": 27.525512, "lon": 0.563417}, {"type": "node", "id": 7069956229, "lat": 27.73437, "lon": -0.028368}, {"type": "node", "id": 7069956230, "lat": 27.460185, "lon": 0.851188}, {"type": "node", "id": 7069956231, "lat": 27.192807, "lon": 0.921748}, {"type": "node", "id": 7069956232, "lat": 27.7448534, "lon": -0.0384166}, {"type": "node", "id": 7069956233, "lat": 27.526903, "lon": 0.784198}, {"type": "node", "id": 7069956234, "lat": 27.177692, "lon": 0.933293}, {"type": "node", "id": 7069956235, "lat": 27.522357, "lon": 0.692405}, {"type": "node", "id": 7069956236, "lat": 27.371553, "lon": 0.877485}, {"type": "node", "id": 7069956237, "lat": 27.143105, "lon": 0.9585}, {"type": "node", "id": 7069956238, "lat": 27.524847, "lon": 0.604568}, {"type": "node", "id": 7069956239, "lat": 27.097155, "lon": 0.988692}, {"type": "node", "id": 7069956240, "lat": 27.232865, "lon": 0.89174}, {"type": "node", "id": 7069956241, "lat": 27.7915304, "lon": -0.147076}, {"type": "node", "id": 7069956242, "lat": 27.721635, "lon": -0.010732}, {"type": "node", "id": 7069956243, "lat": 27.107033, "lon": 0.982633}, {"type": "node", "id": 7069956244, "lat": 27.24481, "lon": 0.885968}, {"type": "node", "id": 7069956245, "lat": 27.804015, "lon": -0.176292, "tags": {"power": "pole"}}, {"type": "node", "id": 7069956246, "lat": 27.131782, "lon": 0.974358}, {"type": "node", "id": 7069956247, "lat": 27.285615, "lon": 0.880825}, {"type": "node", "id": 7069956248, "lat": 27.7545079, "lon": -0.0595261}, {"type": "node", "id": 7069956249, "lat": 27.524137, "lon": 0.615078}, {"type": "node", "id": 7069956250, "lat": 27.211328, "lon": 0.906518}, {"type": "node", "id": 7069956251, "lat": 27.812225, "lon": -0.206015}, {"type": "node", "id": 7069956252, "lat": 27.0379823, "lon": 1.0182256}, {"type": "node", "id": 7069956253, "lat": 27.515298, "lon": 0.814312}, {"type": "node", "id": 7069956254, "lat": 27.82288, "lon": -0.215767}, {"type": "node", "id": 7069956255, "lat": 27.457242, "lon": 0.852095}, {"type": "node", "id": 7069956256, "lat": 27.744057, "lon": -0.0370235}, {"type": "node", "id": 7069956257, "lat": 27.134455, "lon": 0.97121}, {"type": "node", "id": 7069956258, "lat": 27.292803, "lon": 0.880557}, {"type": "node", "id": 7069956259, "lat": 27.8103734, "lon": -0.1972827}, {"type": "node", "id": 7069956260, "lat": 27.184805, "lon": 0.928652}, {"type": "node", "id": 7069956261, "lat": 27.521168, "lon": 0.737092}, {"type": "node", "id": 7069956262, "lat": 27.229902, "lon": 0.893523}, {"type": "node", "id": 7069956263, "lat": 27.105597, "lon": 0.983352}, {"type": "node", "id": 7069956264, "lat": 27.33147, "lon": 0.87895}, {"type": "node", "id": 7069956265, "lat": 27.773955, "lon": -0.10403}, {"type": "node", "id": 7069956266, "lat": 27.268432, "lon": 0.880947}, {"type": "node", "id": 7069956267, "lat": 27.257332, "lon": 0.8822}, {"type": "node", "id": 7069956268, "lat": 27.530878, "lon": 0.369885}, {"type": "node", "id": 7069956269, "lat": 27.487367, "lon": 0.842668}, {"type": "node", "id": 7069956270, "lat": 27.210207, "lon": 0.907488}, {"type": "node", "id": 7069956271, "lat": 27.298077, "lon": 0.880257}, {"type": "node", "id": 7069956272, "lat": 27.31364, "lon": 0.879045}, {"type": "node", "id": 7069956273, "lat": 27.527905, "lon": 0.477098}, {"type": "node", "id": 7069956274, "lat": 27.723935, "lon": -0.014205}, {"type": "node", "id": 7069956275, "lat": 27.527982, "lon": 0.455512}, {"type": "node", "id": 7069956276, "lat": 27.527343, "lon": 0.7742}, {"type": "node", "id": 7069956277, "lat": 27.502373, "lon": 0.839158}, {"type": "node", "id": 7069956278, "lat": 27.139792, "lon": 0.962357}, {"type": "node", "id": 7069956279, "lat": 27.521032, "lon": 0.74058}, {"type": "node", "id": 7069956280, "lat": 27.78961, "lon": -0.142323}, {"type": "node", "id": 7069956281, "lat": 27.52731, "lon": 0.487225}, {"type": "node", "id": 7069956282, "lat": 27.38449, "lon": 0.875105}, {"type": "node", "id": 7069956283, "lat": 27.528338, "lon": 0.468643}, {"type": "node", "id": 7069956284, "lat": 27.054782, "lon": 1.00957}, {"type": "node", "id": 7069956285, "lat": 27.25586, "lon": 0.88241}, {"type": "node", "id": 7069956287, "lat": 27.113232, "lon": 0.98077}, {"type": "node", "id": 7069956288, "lat": 27.7526381, "lon": -0.0549291}, {"type": "node", "id": 7069956289, "lat": 27.808038, "lon": -0.186583}, {"type": "node", "id": 7069956290, "lat": 27.52587, "lon": 0.765778}, {"type": "node", "id": 7069956291, "lat": 27.507917, "lon": 0.834575}, {"type": "node", "id": 7069956292, "lat": 27.521293, "lon": 0.750152}, {"type": "node", "id": 7069956293, "lat": 27.818705, "lon": -0.214263}, {"type": "node", "id": 7069956294, "lat": 27.20035, "lon": 0.917905}, {"type": "node", "id": 7069956295, "lat": 27.32333, "lon": 0.879082}, {"type": "node", "id": 7069956296, "lat": 27.831238, "lon": -0.21631}, {"type": "node", "id": 7069956297, "lat": 27.7749345, "lon": -0.1065821}, {"type": "node", "id": 7069956298, "lat": 27.35017, "lon": 0.877755}, {"type": "node", "id": 7069956299, "lat": 27.476677, "lon": 0.846987}, {"type": "node", "id": 7069956300, "lat": 27.501684, "lon": 0.8394435}, {"type": "node", "id": 7069956301, "lat": 27.523425, "lon": 0.760082}, {"type": "node", "id": 7069956302, "lat": 27.782613, "lon": -0.124837}, {"type": "node", "id": 7069956303, "lat": 27.7611919, "lon": -0.07606}, {"type": "node", "id": 7069956304, "lat": 27.252465, "lon": 0.883275}, {"type": "node", "id": 7069956305, "lat": 27.470165, "lon": 0.849135}, {"type": "node", "id": 7069956306, "lat": 27.523853, "lon": 0.640152}, {"type": "node", "id": 7069956307, "lat": 27.8108871, "lon": -0.199907}, {"type": "node", "id": 7069956308, "lat": 27.524467, "lon": 0.592293}, {"type": "node", "id": 7069956309, "lat": 27.142327, "lon": 0.959157}, {"type": "node", "id": 7069956310, "lat": 27.521395, "lon": 0.75185}, {"type": "node", "id": 7069956311, "lat": 27.531187, "lon": 0.340353}, {"type": "node", "id": 7069956312, "lat": 27.529633, "lon": 0.417128}, {"type": "node", "id": 7069956313, "lat": 27.518777, "lon": 0.806715}, {"type": "node", "id": 7069956314, "lat": 27.523097, "lon": 0.664017}, {"type": "node", "id": 7069956315, "lat": 27.523253, "lon": 0.649832}, {"type": "node", "id": 7069956316, "lat": 27.131127, "lon": 0.974907}, {"type": "node", "id": 7069956317, "lat": 27.183577, "lon": 0.92973}, {"type": "node", "id": 7069956318, "lat": 27.509875, "lon": 0.830788}, {"type": "node", "id": 7069956319, "lat": 27.811933, "lon": -0.205098}, {"type": "node", "id": 7069956320, "lat": 27.0374225, "lon": 1.018488}, {"type": "node", "id": 7069956321, "lat": 27.443777, "lon": 0.856832}, {"type": "node", "id": 7069956323, "lat": 27.7669468, "lon": -0.088081}, {"type": "node", "id": 7069956324, "lat": 27.772988, "lon": -0.101597}, {"type": "node", "id": 7069956325, "lat": 27.522662, "lon": 0.800792}, {"type": "node", "id": 7069956326, "lat": 27.107902, "lon": 0.982305}, {"type": "node", "id": 7069956327, "lat": 27.525727, "lon": 0.54974}, {"type": "node", "id": 7069956328, "lat": 27.191788, "lon": 0.92239}, {"type": "node", "id": 7069956329, "lat": 27.800228, "lon": -0.166768}, {"type": "node", "id": 7069956330, "lat": 27.5271104, "lon": 0.7710595}, {"type": "node", "id": 7069956331, "lat": 27.530228, "lon": 0.360833}, {"type": "node", "id": 7069956332, "lat": 27.522025, "lon": 0.755833}, {"type": "node", "id": 7069956333, "lat": 27.524723, "lon": 0.607413}, {"type": "node", "id": 7069956334, "lat": 27.116217, "lon": 0.979957}, {"type": "node", "id": 7069956335, "lat": 27.382648, "lon": 0.87549}, {"type": "node", "id": 7069956336, "lat": 27.163567, "lon": 0.94385}, {"type": "node", "id": 7069956337, "lat": 27.53018, "lon": 0.405543}, {"type": "node", "id": 7069956338, "lat": 27.24258, "lon": 0.88689}, {"type": "node", "id": 7069956339, "lat": 27.524953, "lon": 0.796768}, {"type": "node", "id": 7069956340, "lat": 27.52184, "lon": 0.721205}, {"type": "node", "id": 7069956341, "lat": 27.427218, "lon": 0.86111}, {"type": "node", "id": 7069956342, "lat": 27.114317, "lon": 0.980517}, {"type": "node", "id": 7069956343, "lat": 27.221373, "lon": 0.898977}, {"type": "node", "id": 7069956344, "lat": 27.52976, "lon": 0.41345}, {"type": "node", "id": 7069956345, "lat": 27.1884, "lon": 0.925248}, {"type": "node", "id": 7069956346, "lat": 27.772015, "lon": -0.099265}, {"type": "node", "id": 7069956347, "lat": 27.171098, "lon": 0.938147}, {"type": "node", "id": 7069956348, "lat": 27.203553, "lon": 0.91494}, {"type": "node", "id": 7069956349, "lat": 27.107703, "lon": 0.98243}, {"type": "node", "id": 7069956350, "lat": 27.749712, "lon": -0.048618}, {"type": "node", "id": 7069956351, "lat": 27.1982294, "lon": 0.9193865}, {"type": "node", "id": 7069956352, "lat": 27.184397, "lon": 0.92904}, {"type": "node", "id": 7069956353, "lat": 27.432138, "lon": 0.859578}, {"type": "node", "id": 7069956354, "lat": 27.8133585, "lon": -0.208666}, {"type": "node", "id": 7069956355, "lat": 27.531327, "lon": 0.327415}, {"type": "node", "id": 7069956356, "lat": 27.447267, "lon": 0.855705}, {"type": "node", "id": 7069956357, "lat": 27.2543338, "lon": 0.8827733}, {"type": "node", "id": 7069956358, "lat": 27.52188, "lon": 0.724453}, {"type": "node", "id": 7069956359, "lat": 27.523972, "lon": 0.637438}, {"type": "node", "id": 7069956360, "lat": 27.5073, "lon": 0.835382}, {"type": "node", "id": 7069956361, "lat": 27.522375, "lon": 0.692862}, {"type": "node", "id": 7069956362, "lat": 27.785815, "lon": -0.132438}, {"type": "node", "id": 7069956363, "lat": 27.7645553, "lon": -0.0831494}, {"type": "node", "id": 7069956364, "lat": 27.525335, "lon": 0.555327}, {"type": "node", "id": 7069956365, "lat": 27.53022, "lon": 0.40123}, {"type": "node", "id": 7069956366, "lat": 27.388557, "lon": 0.874022}, {"type": "node", "id": 7069956367, "lat": 27.190765, "lon": 0.923198}, {"type": "node", "id": 7069956368, "lat": 27.7399665, "lon": -0.0326189}, {"type": "node", "id": 7069956369, "lat": 27.525912, "lon": 0.7941}, {"type": "node", "id": 7069956370, "lat": 27.748066, "lon": -0.0451998}, {"type": "node", "id": 7069956371, "lat": 27.8127479, "lon": -0.2074183}, {"type": "node", "id": 7069956372, "lat": 27.186693, "lon": 0.926878}, {"type": "node", "id": 7069956373, "lat": 27.522555, "lon": 0.673235}, {"type": "node", "id": 7069956374, "lat": 27.732985, "lon": -0.026873}, {"type": "node", "id": 7069956375, "lat": 27.458515, "lon": 0.85167}, {"type": "node", "id": 7069956376, "lat": 27.172148, "lon": 0.937438}, {"type": "node", "id": 7069956377, "lat": 27.836902, "lon": -0.216252}, {"type": "node", "id": 7069956378, "lat": 27.108437, "lon": 0.982117}, {"type": "node", "id": 7069956379, "lat": 27.7774, "lon": -0.112847}, {"type": "node", "id": 7069956380, "lat": 27.528135, "lon": 0.452072}, {"type": "node", "id": 7069956381, "lat": 27.523583, "lon": 0.623692}, {"type": "node", "id": 7069956382, "lat": 27.20848, "lon": 0.909098}, {"type": "node", "id": 7069956383, "lat": 27.526367, "lon": 0.517795}, {"type": "node", "id": 7069956384, "lat": 27.504792, "lon": 0.837752}, {"type": "node", "id": 7069956385, "lat": 27.141622, "lon": 0.959887}, {"type": "node", "id": 7069956386, "lat": 27.521513, "lon": 0.752995}, {"type": "node", "id": 7069956387, "lat": 27.815455, "lon": -0.211678}, {"type": "node", "id": 7069956388, "lat": 27.720408, "lon": -0.009035}, {"type": "node", "id": 7069956389, "lat": 27.7371472, "lon": -0.030608}, {"type": "node", "id": 7069956390, "lat": 27.525617, "lon": 0.795105}, {"type": "node", "id": 7069956391, "lat": 27.109828, "lon": 0.981703}, {"type": "node", "id": 7069956392, "lat": 27.530192, "lon": 0.386787}, {"type": "node", "id": 7069956393, "lat": 27.400615, "lon": 0.870052}, {"type": "node", "id": 7069956394, "lat": 27.415287, "lon": 0.865822}, {"type": "node", "id": 7069956395, "lat": 27.079148, "lon": 0.997623}, {"type": "node", "id": 7069956396, "lat": 27.8115989, "lon": -0.2036025}, {"type": "node", "id": 7069956397, "lat": 27.529158, "lon": 0.427215}, {"type": "node", "id": 7069956398, "lat": 27.524637, "lon": 0.598352}, {"type": "node", "id": 7069956399, "lat": 27.223468, "lon": 0.89759}, {"type": "node", "id": 7069956400, "lat": 27.730797, "lon": -0.02394}, {"type": "node", "id": 7069956401, "lat": 27.52993, "lon": 0.396682}, {"type": "node", "id": 7069956402, "lat": 27.061322, "lon": 1.006885}, {"type": "node", "id": 7069956403, "lat": 27.133742, "lon": 0.972278}, {"type": "node", "id": 7069956404, "lat": 27.521972, "lon": 0.697878}, {"type": "node", "id": 7069956405, "lat": 27.527432, "lon": 0.503353}, {"type": "node", "id": 7069956406, "lat": 27.094322, "lon": 0.990337}, {"type": "node", "id": 7069956407, "lat": 27.042427, "lon": 1.016638}, {"type": "node", "id": 7069956408, "lat": 27.517577, "lon": 0.808907}, {"type": "node", "id": 7069956409, "lat": 27.104593, "lon": 0.98395}, {"type": "node", "id": 7069956410, "lat": 27.735825, "lon": -0.02966}, {"type": "node", "id": 7069956411, "lat": 27.461878, "lon": 0.850785}, {"type": "node", "id": 7069956412, "lat": 27.530938, "lon": 0.372153}, {"type": "node", "id": 7069956413, "lat": 27.521428, "lon": 0.70711}, {"type": "node", "id": 7069956414, "lat": 27.522443, "lon": 0.690632}, {"type": "node", "id": 7069956415, "lat": 27.524318, "lon": 0.589177}, {"type": "node", "id": 7069956416, "lat": 27.520312, "lon": 0.804317}, {"type": "node", "id": 7069956417, "lat": 27.1955442, "lon": 0.9204911}, {"type": "node", "id": 7069956418, "lat": 27.13297, "lon": 0.973178}, {"type": "node", "id": 7069956419, "lat": 27.418595, "lon": 0.86459}, {"type": "node", "id": 7069956420, "lat": 27.529283, "lon": 0.438993}, {"type": "node", "id": 7069956421, "lat": 27.522812, "lon": 0.75854}, {"type": "node", "id": 7069956422, "lat": 27.7617991, "lon": -0.0774053}, {"type": "node", "id": 7069956423, "lat": 27.521047, "lon": 0.742668}, {"type": "node", "id": 7069956424, "lat": 27.119287, "lon": 0.979167}, {"type": "node", "id": 7069956425, "lat": 27.51606, "lon": 0.812258}, {"type": "node", "id": 7069956426, "lat": 27.521742, "lon": 0.727452}, {"type": "node", "id": 7069956427, "lat": 27.528338, "lon": 0.470933}, {"type": "node", "id": 7069956428, "lat": 27.341497, "lon": 0.878295}, {"type": "node", "id": 7069956429, "lat": 27.127347, "lon": 0.976953}, {"type": "node", "id": 7069956430, "lat": 27.206643, "lon": 0.911042}, {"type": "node", "id": 7069956431, "lat": 27.526502, "lon": 0.767833}, {"type": "node", "id": 7069956432, "lat": 27.530272, "lon": 0.357482}, {"type": "node", "id": 7069956433, "lat": 27.506637, "lon": 0.836132}, {"type": "node", "id": 7069956434, "lat": 27.3700377, "lon": 0.8776275}, {"type": "node", "id": 7069956436, "lat": 27.525358, "lon": 0.574997}, {"type": "node", "id": 7069956437, "lat": 27.52757, "lon": 0.481007}, {"type": "node", "id": 7069956438, "lat": 27.7708108, "lon": -0.0962245}, {"type": "node", "id": 7069956439, "lat": 27.0362811, "lon": 1.0192279}, {"type": "node", "id": 7069956440, "lat": 27.270228, "lon": 0.880925}, {"type": "node", "id": 7069956441, "lat": 27.527233, "lon": 0.777873}, {"type": "node", "id": 7069956442, "lat": 27.531138, "lon": 0.332513}, {"type": "node", "id": 7069956443, "lat": 27.821602, "lon": -0.215488}, {"type": "node", "id": 7069956444, "lat": 27.521528, "lon": 0.730427}, {"type": "node", "id": 7069956445, "lat": 27.325988, "lon": 0.878978}, {"type": "node", "id": 7069956446, "lat": 27.52988, "lon": 0.393857}, {"type": "node", "id": 7069956447, "lat": 27.743182, "lon": -0.035758}, {"type": "node", "id": 7069956448, "lat": 27.340077, "lon": 0.878432}, {"type": "node", "id": 7069956449, "lat": 27.52661, "lon": 0.78746}, {"type": "node", "id": 7069956450, "lat": 27.1813162, "lon": 0.9312315}, {"type": "node", "id": 7069956451, "lat": 27.530178, "lon": 0.359162}, {"type": "node", "id": 7069956452, "lat": 27.503995, "lon": 0.838295}, {"type": "node", "id": 7069956453, "lat": 27.140958, "lon": 0.960675}, {"type": "node", "id": 7069956454, "lat": 27.521687, "lon": 0.754138}, {"type": "node", "id": 7069956455, "lat": 27.512292, "lon": 0.823322}, {"type": "node", "id": 7069956456, "lat": 27.814875, "lon": -0.210983}, {"type": "node", "id": 7069956457, "lat": 27.52733, "lon": 0.48497}, {"type": "node", "id": 7069956458, "lat": 27.386328, "lon": 0.874655}, {"type": "node", "id": 7069956459, "lat": 27.056388, "lon": 1.008862}, {"type": "node", "id": 7069956460, "lat": 27.523197, "lon": 0.65191}, {"type": "node", "id": 7069956461, "lat": 27.526275, "lon": 0.541968}, {"type": "node", "id": 7069956462, "lat": 27.746897, "lon": -0.042762}, {"type": "node", "id": 7069956463, "lat": 27.779162, "lon": -0.117237}, {"type": "node", "id": 7069956464, "lat": 27.808615, "lon": -0.188547}, {"type": "node", "id": 7069956465, "lat": 27.509012, "lon": 0.83278}, {"type": "node", "id": 7069956466, "lat": 27.820355, "lon": -0.215057}, {"type": "node", "id": 7069956467, "lat": 27.525598, "lon": 0.570655}, {"type": "node", "id": 7069956468, "lat": 27.1219465, "lon": 0.9784092}, {"type": "node", "id": 7069956469, "lat": 27.391277, "lon": 0.873163}, {"type": "node", "id": 7069956470, "lat": 27.742193, "lon": -0.034592}, {"type": "node", "id": 7069956471, "lat": 27.526428, "lon": 0.791288}, {"type": "node", "id": 7069956472, "lat": 27.526703, "lon": 0.536132}, {"type": "node", "id": 7069956473, "lat": 27.207732, "lon": 0.90987}, {"type": "node", "id": 7069956474, "lat": 27.7563585, "lon": -0.0641351}, {"type": "node", "id": 7069956475, "lat": 27.814083, "lon": -0.209835}, {"type": "node", "id": 7069956476, "lat": 27.522533, "lon": 0.684582}, {"type": "node", "id": 7069956477, "lat": 27.04158, "lon": 1.017025}, {"type": "node", "id": 7069956479, "lat": 27.05357, "lon": 1.010255}, {"type": "node", "id": 7069956480, "lat": 27.52425, "lon": 0.798233}, {"type": "node", "id": 7069956481, "lat": 27.530913, "lon": 0.373282}, {"type": "node", "id": 7069956482, "lat": 27.411383, "lon": 0.867005}, {"type": "node", "id": 7069956483, "lat": 27.80753, "lon": -0.185162}, {"type": "node", "id": 7069956484, "lat": 27.484805, "lon": 0.843567}, {"type": "node", "id": 7069956485, "lat": 27.295183, "lon": 0.880452}, {"type": "node", "id": 7069956486, "lat": 27.524842, "lon": 0.60344}, {"type": "node", "id": 7069956487, "lat": 27.310772, "lon": 0.87911}, {"type": "node", "id": 7069956488, "lat": 27.8175325, "lon": -0.2135035}, {"type": "node", "id": 7069956489, "lat": 27.04618, "lon": 1.014743}, {"type": "node", "id": 7069956490, "lat": 27.523175, "lon": 0.661987}, {"type": "node", "id": 7070033385, "lat": 27.2610149, "lon": 1.2331536}, {"type": "node", "id": 7070033386, "lat": 27.2607336, "lon": 1.2330678}, {"type": "node", "id": 7070033387, "lat": 27.2603306, "lon": 1.2330088}, {"type": "node", "id": 7070033388, "lat": 27.2600755, "lon": 1.2330195}, {"type": "node", "id": 7070033389, "lat": 27.2595843, "lon": 1.233159}, {"type": "node", "id": 7070033390, "lat": 27.2589715, "lon": 1.2334111}, {"type": "node", "id": 7070033391, "lat": 27.2585734, "lon": 1.2336069}, {"type": "node", "id": 7070033392, "lat": 27.2582395, "lon": 1.2337571}, {"type": "node", "id": 7070033393, "lat": 27.2580679, "lon": 1.2338778}, {"type": "node", "id": 7070033394, "lat": 27.2579749, "lon": 1.2340307}, {"type": "node", "id": 7070033395, "lat": 27.2579248, "lon": 1.2341782}, {"type": "node", "id": 7070033396, "lat": 27.2578604, "lon": 1.2344411}, {"type": "node", "id": 7070033397, "lat": 27.2577531, "lon": 1.2348783}, {"type": "node", "id": 7070033398, "lat": 27.2575862, "lon": 1.235463}, {"type": "node", "id": 7070033399, "lat": 27.2574837, "lon": 1.2357286}, {"type": "node", "id": 7070033400, "lat": 27.2573883, "lon": 1.235868}, {"type": "node", "id": 7070033401, "lat": 27.2568423, "lon": 1.2363857}, {"type": "node", "id": 7070033402, "lat": 27.2562844, "lon": 1.2367666}, {"type": "node", "id": 7070033403, "lat": 27.2558695, "lon": 1.2369677}, {"type": "node", "id": 7070033404, "lat": 27.2553354, "lon": 1.2371635}, {"type": "node", "id": 7070033405, "lat": 27.2547822, "lon": 1.2372279}, {"type": "node", "id": 7070033406, "lat": 27.2313551, "lon": 1.2380004}, {"type": "node", "id": 7070033407, "lat": 27.2295139, "lon": 1.2380648}, {"type": "node", "id": 7070033408, "lat": 27.2276059, "lon": 1.2377}, {"type": "node", "id": 7070033409, "lat": 27.226547, "lon": 1.2372923}, {"type": "node", "id": 7070033410, "lat": 27.2257456, "lon": 1.2368095}, {"type": "node", "id": 7070033411, "lat": 27.2243146, "lon": 1.2357151}, {"type": "node", "id": 7070033412, "lat": 27.2234464, "lon": 1.2348246}, {"type": "node", "id": 7070033413, "lat": 27.2197017, "lon": 1.2289077}, {"type": "node", "id": 7070033414, "lat": 27.2153845, "lon": 1.2218213}, {"type": "node", "id": 7070033415, "lat": 27.1995547, "lon": 1.1951923}, {"type": "node", "id": 7070033416, "lat": 27.1975221, "lon": 1.1914801}, {"type": "node", "id": 7070033417, "lat": 27.1955277, "lon": 1.1877143}, {"type": "node", "id": 7070033418, "lat": 27.1940677, "lon": 1.1850214}, {"type": "node", "id": 7070033419, "lat": 27.1927794, "lon": 1.1826825}, {"type": "node", "id": 7070033420, "lat": 27.1917582, "lon": 1.1810624}, {"type": "node", "id": 7070033421, "lat": 27.190823, "lon": 1.1790454}, {"type": "node", "id": 7070033422, "lat": 27.1889907, "lon": 1.1750328}, {"type": "node", "id": 7070033423, "lat": 27.1873779, "lon": 1.1717498}, {"type": "node", "id": 7070033424, "lat": 27.185975, "lon": 1.1690354}, {"type": "node", "id": 7070033425, "lat": 27.184677, "lon": 1.1664176}, {"type": "node", "id": 7070033426, "lat": 27.1837322, "lon": 1.1644113}, {"type": "node", "id": 7070033427, "lat": 27.1826824, "lon": 1.1622333}, {"type": "node", "id": 7070033428, "lat": 27.1815944, "lon": 1.1600876}, {"type": "node", "id": 7070033429, "lat": 27.1804491, "lon": 1.1580062}, {"type": "node", "id": 7070033430, "lat": 27.1791034, "lon": 1.1557209}, {"type": "node", "id": 7070033431, "lat": 27.1771945, "lon": 1.1525023}, {"type": "node", "id": 7070033432, "lat": 27.1752188, "lon": 1.1490154}, {"type": "node", "id": 7070033433, "lat": 27.1745125, "lon": 1.1476314}, {"type": "node", "id": 7070033434, "lat": 27.1733385, "lon": 1.1456144}, {"type": "node", "id": 7070033435, "lat": 27.1718877, "lon": 1.1431038}, {"type": "node", "id": 7070033436, "lat": 27.1709046, "lon": 1.1415052}, {"type": "node", "id": 7070033437, "lat": 27.1699883, "lon": 1.1400676}, {"type": "node", "id": 7070033438, "lat": 27.1689193, "lon": 1.1382973}, {"type": "node", "id": 7070033439, "lat": 27.167182, "lon": 1.1348855}, {"type": "node", "id": 7070033440, "lat": 27.1669148, "lon": 1.134156}, {"type": "node", "id": 7070033441, "lat": 27.1663353, "lon": 1.1320446}, {"type": "node", "id": 7070033442, "lat": 27.1660366, "lon": 1.1304116}, {"type": "node", "id": 7070033443, "lat": 27.1659125, "lon": 1.1291563}, {"type": "node", "id": 7070033444, "lat": 27.1659507, "lon": 1.1273539}, {"type": "node", "id": 7070033445, "lat": 27.1661512, "lon": 1.1251759}, {"type": "node", "id": 7070033446, "lat": 27.1665043, "lon": 1.1216783}, {"type": "node", "id": 7070033447, "lat": 27.1668002, "lon": 1.118406}, {"type": "node", "id": 7070033448, "lat": 27.1671248, "lon": 1.1150265}, {"type": "node", "id": 7070033449, "lat": 27.1674493, "lon": 1.111604}, {"type": "node", "id": 7070033450, "lat": 27.1676975, "lon": 1.1088574}, {"type": "node", "id": 7070033451, "lat": 27.1680602, "lon": 1.1051667}, {"type": "node", "id": 7070033452, "lat": 27.1683179, "lon": 1.1019373}, {"type": "node", "id": 7070033453, "lat": 27.1687188, "lon": 1.0979569}, {"type": "node", "id": 7070033454, "lat": 27.1690624, "lon": 1.094234}, {"type": "node", "id": 7070033455, "lat": 27.1694538, "lon": 1.089685}, {"type": "node", "id": 7070033456, "lat": 27.1697974, "lon": 1.0860908}, {"type": "node", "id": 7070033457, "lat": 27.1702842, "lon": 1.0807049}, {"type": "node", "id": 7070033458, "lat": 27.1706087, "lon": 1.0772502}, {"type": "node", "id": 7070033459, "lat": 27.1708855, "lon": 1.0743856}, {"type": "node", "id": 7070033460, "lat": 27.1711719, "lon": 1.0711241}, {"type": "node", "id": 7070033461, "lat": 27.1715155, "lon": 1.0672295}, {"type": "node", "id": 7070033462, "lat": 27.1718973, "lon": 1.0633671}, {"type": "node", "id": 7070033463, "lat": 27.1720404, "lon": 1.0610711}, {"type": "node", "id": 7070033464, "lat": 27.1720786, "lon": 1.0586357}, {"type": "node", "id": 7070033465, "lat": 27.1720309, "lon": 1.0569727}, {"type": "node", "id": 7070033466, "lat": 27.1718114, "lon": 1.054666}, {"type": "node", "id": 7070033467, "lat": 27.1714773, "lon": 1.0505998}, {"type": "node", "id": 7070033468, "lat": 27.1711146, "lon": 1.0460722}, {"type": "node", "id": 7070033469, "lat": 27.170876, "lon": 1.0435295}, {"type": "node", "id": 7070033470, "lat": 27.1707042, "lon": 1.0421562}, {"type": "node", "id": 7070033471, "lat": 27.1702556, "lon": 1.0403216}, {"type": "node", "id": 7070033472, "lat": 27.1698451, "lon": 1.0390663}, {"type": "node", "id": 7070033473, "lat": 27.1693965, "lon": 1.0379827}, {"type": "node", "id": 7070033474, "lat": 27.1682797, "lon": 1.035794}, {"type": "node", "id": 7070033475, "lat": 27.167287, "lon": 1.0337555}, {"type": "node", "id": 7070033476, "lat": 27.1656452, "lon": 1.030451}, {"type": "node", "id": 7070033477, "lat": 27.1637743, "lon": 1.026696}, {"type": "node", "id": 7070033478, "lat": 27.1621516, "lon": 1.02337}, {"type": "node", "id": 7070033479, "lat": 27.1605766, "lon": 1.0202372}, {"type": "node", "id": 7070033480, "lat": 27.1594024, "lon": 1.0178554}, {"type": "node", "id": 7070033481, "lat": 27.1582569, "lon": 1.015538}, {"type": "node", "id": 7070033482, "lat": 27.157646, "lon": 1.0141003}, {"type": "node", "id": 7070033483, "lat": 27.1568346, "lon": 1.0121262}, {"type": "node", "id": 7070033484, "lat": 27.1556986, "lon": 1.0091972}, {"type": "node", "id": 7070033485, "lat": 27.1548776, "lon": 1.0071158}, {"type": "node", "id": 7070033486, "lat": 27.1544098, "lon": 1.0059035}, {"type": "node", "id": 7070033487, "lat": 27.1537416, "lon": 1.0043156}, {"type": "node", "id": 7070033488, "lat": 27.152997, "lon": 1.0026955}, {"type": "node", "id": 7070033489, "lat": 27.1517655, "lon": 1.0002601}, {"type": "node", "id": 7070033490, "lat": 27.1496079, "lon": 0.996505}, {"type": "node", "id": 7070033491, "lat": 27.1474933, "lon": 0.9927392}, {"type": "node", "id": 7070033492, "lat": 27.1463333, "lon": 0.990631}, {"type": "node", "id": 7070033493, "lat": 27.1455409, "lon": 0.9891933}, {"type": "node", "id": 7070033494, "lat": 27.1444573, "lon": 0.9872943}, {"type": "node", "id": 7070033495, "lat": 27.1433069, "lon": 0.9851432}, {"type": "node", "id": 7070033496, "lat": 27.1422949, "lon": 0.9830189}, {"type": "node", "id": 7070033497, "lat": 27.1411779, "lon": 0.9800362}, {"type": "node", "id": 7070033498, "lat": 27.1391538, "lon": 0.9743929}, {"type": "node", "id": 7070033499, "lat": 27.136697, "lon": 0.967491}, {"type": "node", "id": 7070049391, "lat": 27.2608933, "lon": 1.2221646}, {"type": "node", "id": 7070049392, "lat": 27.2609267, "lon": 1.2223873}, {"type": "node", "id": 7070049393, "lat": 27.260972, "lon": 1.2224382}, {"type": "node", "id": 7070049394, "lat": 27.2610697, "lon": 1.2224382}, {"type": "node", "id": 7070049395, "lat": 27.26127, "lon": 1.2224328}, {"type": "node", "id": 7070049396, "lat": 27.2615585, "lon": 1.2224704}, {"type": "node", "id": 7070049397, "lat": 27.2618303, "lon": 1.2225777}, {"type": "node", "id": 7070049398, "lat": 27.2622786, "lon": 1.2228727}, {"type": "node", "id": 7070049399, "lat": 27.2630797, "lon": 1.2235433}, {"type": "node", "id": 7070049400, "lat": 27.2637997, "lon": 1.2240958}, {"type": "node", "id": 7070049401, "lat": 27.2655283, "lon": 1.2251419}, {"type": "node", "id": 7070049402, "lat": 27.2664009, "lon": 1.2257588}, {"type": "node", "id": 7070049403, "lat": 27.2666608, "lon": 1.2259412}, {"type": "node", "id": 7070049404, "lat": 27.2667442, "lon": 1.2260565}, {"type": "node", "id": 7321826950, "lat": 26.7547315, "lon": 0.2347853}, {"type": "node", "id": 7776141249, "lat": 26.9590133, "lon": 1.0807558}, {"type": "node", "id": 8255958617, "lat": 26.7263187, "lon": 0.1767389}, {"type": "node", "id": 8255958670, "lat": 26.7254829, "lon": 0.1712065}, {"type": "node", "id": 8255958672, "lat": 26.7260533, "lon": 0.1732991}, {"type": "node", "id": 8255958676, "lat": 26.7258862, "lon": 0.1723225}, {"type": "node", "id": 8255959141, "lat": 26.7271224, "lon": 0.180164}, {"type": "node", "id": 8255959142, "lat": 26.7338012, "lon": 0.1965871}, {"type": "node", "id": 8255959143, "lat": 26.7329724, "lon": 0.1954848}, {"type": "node", "id": 8255959144, "lat": 26.7302798, "lon": 0.1886156}, {"type": "node", "id": 8255959145, "lat": 26.7300306, "lon": 0.1869607}, {"type": "node", "id": 8255959146, "lat": 26.7301456, "lon": 0.1856142}, {"type": "node", "id": 8255959147, "lat": 26.730124, "lon": 0.1849061}, {"type": "node", "id": 8255959148, "lat": 26.7300306, "lon": 0.1843777}, {"type": "node", "id": 8255959149, "lat": 26.7297575, "lon": 0.1837447}, {"type": "node", "id": 8255959150, "lat": 26.7273883, "lon": 0.1806334}, {"type": "node", "id": 8255959395, "lat": 26.734503, "lon": 0.1973221}, {"type": "node", "id": 8255959410, "lat": 26.7419819, "lon": 0.206877}, {"type": "node", "id": 8255959443, "lat": 26.7391674, "lon": 0.2012834}, {"type": "node", "id": 8255959479, "lat": 26.7396916, "lon": 0.2020025}, {"type": "node", "id": 8255959480, "lat": 26.7403766, "lon": 0.2031988}, {"type": "node", "id": 8255959495, "lat": 26.742269, "lon": 0.207552}, {"type": "node", "id": 9224877990, "lat": 27.5258282, "lon": 0.7943855}, {"type": "node", "id": 9336344520, "lat": 26.7258431, "lon": 0.1722005}, {"type": "node", "id": 10038932316, "lat": 27.7272655, "lon": -0.0189354}, {"type": "node", "id": 10038967022, "lat": 27.726845, "lon": -0.0183388}, {"type": "node", "id": 10038967032, "lat": 27.7270944, "lon": -0.0186926}, {"type": "node", "id": 10038967035, "lat": 27.7270588, "lon": -0.0186421}, {"type": "node", "id": 11073449205, "lat": 26.7434235, "lon": 0.2103308}, {"type": "node", "id": 11073449206, "lat": 26.7446116, "lon": 0.2133965}, {"type": "node", "id": 11096579526, "lat": 27.8195333, "lon": -0.2147001}, {"type": "node", "id": 11096579527, "lat": 27.8169902, "lon": -0.2130827}, {"type": "node", "id": 11096579528, "lat": 27.8120795, "lon": -0.2055913}, {"type": "node", "id": 11096579546, "lat": 27.8158648, "lon": -0.2120824}, {"type": "node", "id": 11096692572, "lat": 27.7698717, "lon": -0.0941831}, {"type": "node", "id": 11096692573, "lat": 27.7680493, "lon": -0.0904034}, {"type": "node", "id": 11096731952, "lat": 27.7587475, "lon": -0.070121}, {"type": "node", "id": 11096731953, "lat": 27.7632073, "lon": -0.0803214}, {"type": "node", "id": 11096849088, "lat": 27.7436294, "lon": -0.0363734}, {"type": "node", "id": 11096849089, "lat": 27.7444603, "lon": -0.037685}, {"type": "node", "id": 11096849090, "lat": 27.7454359, "lon": -0.0396028}, {"type": "node", "id": 11096849091, "lat": 27.7460009, "lon": -0.0408393}, {"type": "node", "id": 11096849101, "lat": 27.8089328, "lon": -0.190012}, {"type": "node", "id": 11096922137, "lat": 27.740738, "lon": -0.0332513}, {"type": "node", "id": 11097026899, "lat": 27.8342281, "lon": -0.2164194}, {"type": "node", "id": 11097026900, "lat": 27.8332319, "lon": -0.2164006}, {"type": "node", "id": 11136340650, "lat": 26.9390843, "lon": 1.0234559}, {"type": "node", "id": 11136340651, "lat": 26.9328743, "lon": 1.0079446}, {"type": "node", "id": 11136340652, "lat": 26.929536, "lon": 1.0010728}, {"type": "node", "id": 11136340653, "lat": 26.924404, "lon": 0.9880051}, {"type": "node", "id": 11136340654, "lat": 26.922785, "lon": 0.9843358}, {"type": "node", "id": 11136657122, "lat": 27.0368259, "lon": 1.0188371}, {"type": "node", "id": 11359833600, "lat": 26.780497, "lon": 0.3248706}, {"type": "node", "id": 11359833601, "lat": 26.7779256, "lon": 0.3180657}, {"type": "node", "id": 11359833602, "lat": 26.7968595, "lon": 0.3635895}, {"type": "node", "id": 11359833603, "lat": 26.7984677, "lon": 0.3669747}, {"type": "node", "id": 11359833604, "lat": 26.8005267, "lon": 0.3741033}, {"type": "node", "id": 11359833605, "lat": 26.8014243, "lon": 0.37725}, {"type": "node", "id": 11359833606, "lat": 26.8044514, "lon": 0.3862544}, {"type": "node", "id": 11359833607, "lat": 26.8062714, "lon": 0.390819}, {"type": "node", "id": 11359833608, "lat": 26.8082397, "lon": 0.3956367}, {"type": "node", "id": 11359833609, "lat": 26.8103238, "lon": 0.4010516}, {"type": "node", "id": 11359833610, "lat": 26.8137743, "lon": 0.4082908}, {"type": "node", "id": 11359833611, "lat": 26.821364, "lon": 0.425336}, {"type": "node", "id": 11359833612, "lat": 26.8242169, "lon": 0.431007}, {"type": "node", "id": 11359833613, "lat": 26.8247109, "lon": 0.431919}, {"type": "node", "id": 11359833614, "lat": 26.8282142, "lon": 0.4378374}, {"type": "node", "id": 11359833615, "lat": 26.8325021, "lon": 0.4458084}, {"type": "node", "id": 11359833616, "lat": 26.8319359, "lon": 0.4445611}, {"type": "node", "id": 11359833617, "lat": 26.8343055, "lon": 0.4497209}, {"type": "node", "id": 11359833618, "lat": 26.8360083, "lon": 0.4529904}, {"type": "node", "id": 11359833619, "lat": 26.8364128, "lon": 0.4537178}, {"type": "node", "id": 11359833620, "lat": 26.838363, "lon": 0.4569388}, {"type": "node", "id": 11359833621, "lat": 26.8418826, "lon": 0.4632529}, {"type": "node", "id": 11359833622, "lat": 26.8437324, "lon": 0.4663876}, {"type": "node", "id": 11359833623, "lat": 26.8483292, "lon": 0.4731349}, {"type": "node", "id": 11359833624, "lat": 26.8530993, "lon": 0.4808773}, {"type": "node", "id": 11359833625, "lat": 26.8534496, "lon": 0.4815079}, {"type": "node", "id": 11359833626, "lat": 26.8542391, "lon": 0.4833241}, {"type": "node", "id": 11359833627, "lat": 26.8540216, "lon": 0.482722}, {"type": "node", "id": 11359833628, "lat": 26.8544317, "lon": 0.4839752}, {"type": "node", "id": 11359833629, "lat": 26.8554679, "lon": 0.4885198}, {"type": "node", "id": 11359833630, "lat": 26.8561528, "lon": 0.4907968}, {"type": "node", "id": 11359833631, "lat": 26.85641, "lon": 0.4915092}, {"type": "node", "id": 11359833632, "lat": 26.8570528, "lon": 0.4931298}, {"type": "node", "id": 11359833633, "lat": 26.8580144, "lon": 0.4951679}, {"type": "node", "id": 11359833634, "lat": 26.8597289, "lon": 0.4984112}, {"type": "node", "id": 11359833635, "lat": 26.8601896, "lon": 0.4996077}, {"type": "node", "id": 11359833636, "lat": 26.8604522, "lon": 0.5003507}, {"type": "node", "id": 11359833637, "lat": 26.8679894, "lon": 0.5489112}, {"type": "node", "id": 11359833638, "lat": 26.8703879, "lon": 0.5571619}, {"type": "node", "id": 11359833639, "lat": 26.8716866, "lon": 0.5638}, {"type": "node", "id": 11359833640, "lat": 26.8743851, "lon": 0.5794909}, {"type": "node", "id": 11359833641, "lat": 26.8736238, "lon": 0.5757418}, {"type": "node", "id": 11359833642, "lat": 26.878539, "lon": 0.5994436}, {"type": "node", "id": 11359833643, "lat": 26.8797, "lon": 0.6034964}, {"type": "node", "id": 11359833644, "lat": 26.8817842, "lon": 0.6120818}, {"type": "node", "id": 11359833645, "lat": 26.8821496, "lon": 0.6136064}, {"type": "node", "id": 11359833646, "lat": 26.8831155, "lon": 0.6186835}, {"type": "node", "id": 11359833647, "lat": 26.8990561, "lon": 0.8425032}, {"type": "node", "id": 11359833648, "lat": 26.8975643, "lon": 0.8404011}, {"type": "node", "id": 11359833649, "lat": 26.9026506, "lon": 0.8457863}, {"type": "node", "id": 11359833650, "lat": 26.9054186, "lon": 0.8496204}, {"type": "node", "id": 11359833651, "lat": 26.9064732, "lon": 0.8514822}, {"type": "node", "id": 11359833652, "lat": 26.9087632, "lon": 0.8546784}, {"type": "node", "id": 11359833653, "lat": 26.9082083, "lon": 0.8539579}, {"type": "node", "id": 11359833654, "lat": 26.9104967, "lon": 0.8569609}, {"type": "node", "id": 11359833655, "lat": 26.9101612, "lon": 0.8564862}, {"type": "node", "id": 11359833656, "lat": 26.9161431, "lon": 0.8674162}, {"type": "node", "id": 11359833657, "lat": 26.9163738, "lon": 0.8679745}, {"type": "node", "id": 11359833658, "lat": 26.9164964, "lon": 0.8682434}, {"type": "node", "id": 11359833659, "lat": 26.9177589, "lon": 0.870628}, {"type": "node", "id": 11359833660, "lat": 26.9180081, "lon": 0.8710042}, {"type": "node", "id": 11359833661, "lat": 26.9195121, "lon": 0.8733305}, {"type": "node", "id": 11359833662, "lat": 26.9198486, "lon": 0.8740574}, {"type": "node", "id": 11359833663, "lat": 26.9202312, "lon": 0.8753117}, {"type": "node", "id": 11359833664, "lat": 26.920358, "lon": 0.8760955}, {"type": "node", "id": 11359833665, "lat": 26.9203773, "lon": 0.8773966}, {"type": "node", "id": 11359833666, "lat": 26.920265, "lon": 0.8782701}, {"type": "node", "id": 11359833667, "lat": 26.9199746, "lon": 0.8794756}, {"type": "node", "id": 11359833668, "lat": 26.9200661, "lon": 0.8791654}, {"type": "node", "id": 11359839069, "lat": 26.919802, "lon": 0.8798908}, {"type": "node", "id": 11359839070, "lat": 26.9191363, "lon": 0.8813793}, {"type": "node", "id": 11359839071, "lat": 26.9189128, "lon": 0.8818855}, {"type": "node", "id": 11359839072, "lat": 26.9184317, "lon": 0.8831155}, {"type": "node", "id": 11359839073, "lat": 26.9182686, "lon": 0.8835743}, {"type": "node", "id": 11359839074, "lat": 26.9171908, "lon": 0.8894956}, {"type": "node", "id": 11359839075, "lat": 26.917146, "lon": 0.8899249}, {"type": "node", "id": 11359839076, "lat": 26.91691, "lon": 0.8912743}, {"type": "way", "id": 248920364, "nodes": [4360760404, 8255958670, 4360760410, 9336344520, 8255958676, 429529483, 8255958672, 429529484, 429529485, 8255958617, 429529489, 429529490, 429529491, 429529492, 429529493, 8255959141, 2118812439, 8255959150, 429529498, 8255959149, 429529499, 8255959148, 2956271934, 8255959147, 429529502, 8255959146, 429529504, 8255959145, 429529505, 429529506, 429529507, 8255959144, 429529509, 429529511, 429529513, 2956270835, 429529514, 429529515, 8255959143, 429529516, 8255959142, 429529517, 8255959395, 429529518, 429529519, 429529520, 429529521, 429529522, 2956270734, 8255959443, 429529523, 8255959479, 429529524, 8255959480, 429529525, 8255959410, 8255959495, 11073449205, 11073449206, 429529528, 429529529, 429529530, 2956272135, 429529531, 429529532, 429529533, 429529535, 429529536, 429529537, 429529538, 429529539, 429529540, 429529541, 429529542, 429529543, 7321826950, 429529544, 429529548, 429529550, 429529551, 429529552, 429529554, 2338542290, 429529556, 429529562, 429529568, 429529570, 429529573, 429529575, 429529577, 429529581, 429529584, 429529586, 429529589, 429529591, 429529593, 429529596, 429529599, 429529603, 429529605, 429529606, 429529607, 429529618, 429529621, 429529624, 429529627, 429529630, 429529632, 429529635, 429529646, 2956300633, 429529649, 11359833601, 429529651, 11359833600, 429529653, 429529655, 429529656, 429529657, 429529658, 429529666, 429529668, 429529670, 429529671, 11359833602, 429529673, 11359833603, 429529674, 11359833604, 11359833605, 429529675, 429529676, 11359833606, 429529677, 11359833607, 429529678, 11359833608, 429529680, 11359833609, 429529681, 429529683, 11359833610, 429529684, 429529685, 429529687, 429529688, 429529690, 11359833611, 429529691, 11359833612, 11359833613, 429529693, 3343041912, 11359833614, 429529695, 429529696, 429529697, 11359833616, 11359833615, 429529699, 11359833617, 429529701, 11359833618, 11359833619, 429529702, 11359833620, 429529704, 429529706, 11359833621, 429529707, 11359833622, 429529708, 429529709, 11359833623, 429529710, 429529711, 11359833624, 11359833625, 429529712, 11359833627, 11359833626, 11359833628, 429529714, 429529716, 11359833629, 429529717, 11359833630, 11359833631, 429529719, 11359833632, 429529720, 11359833633, 429529722, 429529724, 11359833634, 11359833635, 11359833636, 429529725, 429529727, 429529728, 429529730, 429529732, 429529733, 429529735, 3343029691, 429529736, 429529738, 429529739, 429529740, 429529741, 429529742, 429529743, 429529745, 429529747, 429529749, 11359833637, 429529750, 11359833638, 429529752, 11359833639, 429529753, 429529755, 11359833641, 11359833640, 429529756, 429529758, 429529760, 11359833642, 11359833643, 429529762, 429529764, 11359833644, 11359833645, 429529766, 429529768, 11359833646, 3954794592, 429529770, 429529772, 429529774, 429529776, 429529778, 429529780, 3954794593, 429529781, 3954794594, 429529783, 429529784, 429529785, 429529788, 429529789, 3954794595, 429529792, 3954794596, 429529794, 429529796, 429529798, 429529800, 3954794597, 429529801, 3954794598, 3954794599, 429529803, 3954794600, 429529804, 429529816, 3954794601, 429529818, 429529820, 3954814010, 429529822, 429529824, 429529827, 429529828, 429529830, 429529831, 429529832, 429529833, 429529834, 429529836, 429529837, 429529839, 429529840, 3954814011, 429529842, 429529843, 429529845, 3954814012, 429529847, 429529848, 3954814013, 429529849, 429529851, 3954814014, 429529853, 429529855, 429529857, 429529859, 429529862, 429529863, 3954814015, 3954814016, 429529866, 3954814017, 3954814018, 429529868, 429529869, 3954814019, 3954814020, 429529870, 11359833648, 429529871, 3954814021, 11359833647, 429529872, 429529873, 11359833649, 429529874, 3954814022, 429529877, 11359833650, 429529878, 11359833651, 429529881, 3954814023, 11359833653, 11359833652, 429529882, 11359833655, 11359833654, 429529884, 429529886, 3954814024, 429529888, 429529890, 11359833656, 11359833657, 11359833658, 429529892, 3954814025, 429529894, 11359833659, 11359833660, 429529895, 3954814026, 3954814027, 11359833661, 3954814028, 11359833662, 3954814029, 429529897, 11359833663, 3954814030, 11359833664, 3954814031, 429529898, 11359833665, 3954814032, 11359833666, 429529900, 11359833668, 11359833667, 11359839069, 429529902, 11359839070, 11359839071, 429529903, 11359839072, 11359839073, 429529905, 3954814033, 3954814034, 429529907, 11359839074, 11359839075, 429529908, 11359839076, 429529910, 429529912, 3954814035, 429529913, 429529914, 3954814036, 3954814037, 429529916, 3954814038, 429529917, 429529918, 429529919, 429529920, 429529922, 429529923, 429529926, 429529928, 429529930, 429529932, 429529934, 429529936, 429529938, 429529941, 429529942, 429529945, 429529946, 429529949, 429529950, 2956490233, 429529954, 429529958, 429529961, 429529962, 429529965, 429529982, 429529987, 429529989, 429529993, 429529994, 429529996, 429529997, 429529998, 429530000, 429530002, 429530005, 429530006, 429530010, 11136340654, 429530014, 11136340653, 429530017, 429530018, 2956409058, 429530021, 429530024, 429530025, 11136340652, 429530028, 429530030, 429530032, 11136340651, 429530034, 429530036, 429530038, 429530039, 429530040, 429530041, 429530043, 2956408147, 11136340650, 2956408148, 429530052, 429530059, 2956407948, 429530067, 2956407949, 429530072, 2956408149, 2956408150, 429530078, 429530081, 429530083, 429530087, 429530090, 429530095, 429530099, 429530103, 429530107, 429530110, 429530111, 429530114, 429530115, 3044821153, 4315960732, 429530119, 429530121, 429530122, 429530123, 3012156771, 429530124, 3012156742, 429530125, 2956408151, 429530127, 429530138, 429530141, 429530142, 7776141249, 429530145], "tags": {"highway": "primary", "lanes": "2", "lanes:backward": "1", "lanes:forward": "1", "oneway": "no", "ref": "RN 52", "ref:ar": "\u0637\u0648 52", "surface": "asphalt"}}, {"type": "way", "id": 757018408, "nodes": [5142402089, 7069956439, 11136657122, 7069956320, 7069956252, 7069956224, 7069956477, 7069956407, 7069956489, 7069956217, 7069956479, 7069956284, 7069956459, 7069956402, 7069956176, 7069956395, 7069956406, 7069956239, 7069956409, 7069956263, 7069956243, 7069956218, 7069956349, 7069956326, 7069956378, 7069956391, 7069956287, 7069956342, 7069956334, 7069956193, 7069956424, 7069956468, 7069956429, 7069956206, 7069956187, 7069956316, 7069956246, 7069956418, 7069956403, 7069956257, 7070033499, 7069956278, 7069956201, 7069956453, 7069956385, 7069956309, 7069956237, 7069956336, 7069956195, 7069956347, 7069956376, 7069956196, 7069956234, 7069956189, 7069956450, 7069956211, 7069956317, 7069956352, 7069956260, 7069956372, 7069956345, 7069956367, 7069956328, 7069956231, 7069956186, 7069956417, 7069956351, 7069956199, 7069956294, 7069956227, 7069956184, 7069956348, 7069956221, 7069956430, 7069956473, 7069956382, 7069956270, 7069956250, 7069956169, 7069956343, 7069956399, 7069956262, 7069956240, 7069956174, 7069956338, 7069956244, 7069956304, 7069956357, 7069956285, 7069956267, 7069956178, 7069956266, 7069956440, 7069956208, 7069956247, 7069956258, 7069956485, 7069956271, 7069956181, 7069956487, 7069956272, 7069956183, 7069956295, 7069956445, 7069956264, 7069956448, 7069956428, 7069956298, 7069956434, 7069956236, 7069956335, 7069956282, 7069956458, 7069956366, 7069956469, 7069956393, 7069956482, 7069956394, 7069956419, 7069956341, 7069956171, 7069956353, 7069956215, 7069956321, 7069956356, 7069956255, 7069956375, 7069956230, 7069956411, 7069956305, 7069956205, 7069956299, 7069956484, 7069956269, 7069956168, 7069956167, 7069956300, 7069956277, 7069956200, 7069956452, 7069956384, 7069956179, 7069956433, 7069956360, 7069956291, 7069956212, 7069956465, 7069956318, 7069956455, 7069956253, 7069956425, 7069956226, 7069956408, 7069956313, 7069956416, 7069956325, 7069956175, 7069956480, 7069956339, 7069956390, 9224877990, 7069956369, 7069956164, 7069956471, 7069956449, 7069956233, 7069956188, 7069956441, 7069956166, 7069956276, 7069956330, 7069956431, 7069956290, 7069956210, 7069956301, 7069956421, 7069956332, 7069956454, 7069956386, 7069956310, 7069956292, 7069956423, 7069956279, 7069956261, 7069956444, 7069956426, 7069956358, 7069956340, 7069956413, 7069956209, 7069956404, 7069956361, 7069956235, 7069956414, 7069956191, 7069956223, 7069956476, 7069956373, 7069956314, 7069956490, 7069956460, 7069956315, 7069956306, 7069956359, 7069956207, 7069956198, 7069956381, 7069956249, 7069956333, 7069956238, 7069956486, 7069956398, 7069956308, 7069956415, 7069956213, 7069956192, 7069956436, 7069956216, 7069956467, 7069956228, 7069956364, 7069956219, 7069956327, 7069956461, 7069956165, 7069956472, 7069956190, 7069956383, 7069956405, 7069956180, 7069956281, 7069956457, 7069956437, 7069956273, 7069956427, 7069956283, 7069956275, 7069956197, 7069956380, 7069956420, 7069956397, 7069956312, 7069956344, 7069956337, 7069956185, 7069956365, 7069956401, 7069956446, 7069956392, 7069956177, 7069956481, 7069956412, 7069956268, 7069956331, 7069956451, 7069956432, 7069956170, 7069956311, 7069956214, 7069956442, 7069956225, 7069956355, 7069956162, 7069956161, 7069956160, 7069956159, 7069956158, 7069956157, 7069956156, 7069956155, 7069956154, 7069956153, 7069956152, 7069956151, 7069956150, 7069956149, 7069956148, 7069956147, 7069956146, 7069956145, 7069956144, 7069956143, 7069956142, 7069956141, 7069956140, 7069956139, 7069956138, 7069956137, 7069956136, 7069956135, 7069956134, 7069956133, 7069956132, 7069956131, 7069956130, 7069956129, 7069956128, 7069956127, 7069956126, 7069956125, 7069956124, 7069956123, 7069956122, 7069956121, 7069956120, 7069956119, 7069956118, 7069956117, 7069956116, 7069956115, 7069956114, 7069956113, 7069956112, 7069956111, 7069956110, 7069956109, 7069956108, 7069956107, 7069956106, 7069956105, 7069956104, 7069956103, 7069956102, 7069956101, 7069956100, 7069956099, 7069956098, 7069956097, 7069956096, 7069956095, 7069956388, 7069956242, 7069956274, 10038967022, 10038967035, 10038967032, 10038932316, 7069956400, 7069956374, 7069956229, 7069956410, 7069956389, 7069956368, 11096922137, 7069956220, 7069956470, 7069956447, 11096849088, 7069956256, 11096849089, 7069956232, 11096849090, 11096849091, 7069956462, 7069956370, 7069956350, 7069956288, 7069956248, 7069956474, 11096731952, 7069956303, 7069956422, 11096731953, 7069956363, 7069956323, 7069956172, 11096692573, 11096692572, 7069956438, 7069956346, 7069956324, 7069956203, 7069956265, 7069956297, 7069956379, 7069956463, 7069956302, 7069956202, 7069956362, 7069956280, 7069956241, 7069956163, 7069956329, 7069956245, 7069956483, 7069956289, 7069956464, 11096849101, 7069956222, 3789013335, 7069956259, 7069956307, 7069956396, 7069956319, 11096579528, 7069956251, 7069956371, 7069956354, 7069956475, 7069956456, 7069956387, 11096579546, 7069956182, 11096579527, 7069956488, 7069956293, 11096579526, 7069956466, 7069956443, 7069956254, 7069956173, 7069956296, 11097026900, 11097026899, 7069956194, 7069956377, 7069956204, 7069956094], "tags": {"highway": "secondary", "lanes": "2", "lanes:backward": "1", "lanes:forward": "1", "maxspeed": "110", "name": "Route Aoulef Adrar", "name:fr": "Route Aoulef Adrar", "ref": "RN", "smoothness": "good", "surface": "asphalt"}}, {"type": "way", "id": 757028209, "nodes": [7070033499, 7070033498, 7070033497, 7070033496, 7070033495, 7070033494, 7070033493, 7070033492, 7070033491, 7070033490, 7070033489, 7070033488, 7070033487, 7070033486, 7070033485, 7070033484, 7070033483, 7070033482, 7070033481, 7070033480, 7070033479, 7070033478, 7070033477, 7070033476, 7070033475, 7070033474, 7070033473, 7070033472, 7070033471, 7070033470, 7070033469, 7070033468, 7070033467, 7070033466, 7070033465, 7070033464, 7070033463, 7070033462, 7070033461, 7070033460, 7070033459, 7070033458, 7070033457, 7070033456, 7070033455, 7070033454, 7070033453, 7070033452, 7070033451, 7070033450, 7070033449, 7070033448, 7070033447, 7070033446, 7070033445, 7070033444, 7070033443, 7070033442, 7070033441, 7070033440, 7070033439, 7070033438, 7070033437, 7070033436, 7070033435, 7070033434, 7070033433, 7070033432, 7070033431, 7070033430, 7070033429, 7070033428, 7070033427, 7070033426, 7070033425, 7070033424, 7070033423, 7070033422, 7070033421, 7070033420, 7070033419, 7070033418, 7070033417, 7070033416, 7070033415, 7070033414, 7070033413, 7070033412, 7070033411, 7070033410, 7070033409, 7070033408, 7070033407, 7070033406, 7070033405, 7070033404, 7070033403, 7070033402, 7070033401, 7070033400, 7070033399, 7070033398, 7070033397, 7070033396, 7070033395, 7070033394, 7070033393, 7070033392, 7070033391, 7070033390, 7070033389, 7070033388, 7070033387, 7070033386, 7070033385, 7069953784, 7069953783, 7069953782, 7069953781, 7069953780, 7069953779, 7069953778, 7069953777, 7069953776, 7069953775, 7069953774, 7069953773, 7069953772, 7069953771, 7069953770, 7069953769, 7069953768, 7069953767, 7069953766, 7070049404, 7070049403, 7070049402, 7070049401, 7070049400, 7070049399, 7070049398, 7070049397, 7070049396, 7070049395, 7070049394, 7070049393, 7070049392, 7070049391], "tags": {"highway": "unclassified", "name": "Route Cimenterie Aoulef"}}]}